Workbook

Sheet Cover
B2: Dhaka Tesla Pool — SRS Traceability Tracker
B3: Share a seat. Split the fare. Survive Dhaka traffic.
B5: Document | C5: DTP-SRS-001 — docs/SRS.md (ISO/IEC/IEEE 29148:2018, tailored)
B6: SRS version | C6: 0.3 (Draft for review) — see SRS revision history
B7: Author | C7: Golam Mahadi Ahmed
B8: Created | C8: 2026-09-23
B9: Source brief | C9: Dhaka_Tesla_Pool_PRD_Internship.pdf (RoBenDevs)
B10: Last updated | C10: 2026-09-24 — Phase 4 (feature/ride-request): state machines, audit trail, ride requests, expiry, unmatched cancellation
B11: How to maintain this workbook
B12: • | C12: Requirement text lives in docs/SRS.md; change it there first, then mirror the row here (same ID).
B13: • | C13: Yellow cells are the ones to edit: Status, Evidence and Notes columns on each sheet (dropdowns enforce allowed values).
B14: • | C14: Requirement status flow: Proposed → Approved (SRS reviewed) → In Progress → Implemented (merged to master) → Verified (linked tests pass).
B15: • | C15: When a test is written, set Test_Cases.Status and put the test file path in 'Test file / evidence'.
B16: • | C16: When a task is merged, set Implementation_Tasks.Status = Done and paste the commit hash / PR link.
B17: • | C17: Never reuse or delete an ID — set Status = Withdrawn instead. Blue numbers on Zones_Distances / Fare_Calculator are reference inputs.
B19: Requirements by type | F19: By priority
B20: Type | C20: Count | D20: of which Must | F20: Priority | G20: Count
B21: FR — Functional | C21: =COUNTIF(Requirements_RTM!$B$2:$B$142,"FR") | D21: =COUNTIFS(Requirements_RTM!$B$2:$B$142,"FR",Requirements_RTM!$E$2:$E$142,"M") | F21: M | G21: =COUNTIF(Requirements_RTM!$E$2:$E$142,"M")
B22: BR — Business rule | C22: =COUNTIF(Requirements_RTM!$B$2:$B$142,"BR") | D22: =COUNTIFS(Requirements_RTM!$B$2:$B$142,"BR",Requirements_RTM!$E$2:$E$142,"M") | F22: S | G22: =COUNTIF(Requirements_RTM!$E$2:$E$142,"S")
B23: NFR — Non-functional | C23: =COUNTIF(Requirements_RTM!$B$2:$B$142,"NFR") | D23: =COUNTIFS(Requirements_RTM!$B$2:$B$142,"NFR",Requirements_RTM!$E$2:$E$142,"M") | F23: C | G23: =COUNTIF(Requirements_RTM!$E$2:$E$142,"C")
B24: DC — Design constraint | C24: =COUNTIF(Requirements_RTM!$B$2:$B$142,"DC") | D24: =COUNTIFS(Requirements_RTM!$B$2:$B$142,"DC",Requirements_RTM!$E$2:$E$142,"M") | F24: W | G24: =COUNTIF(Requirements_RTM!$E$2:$E$142,"W")
B25: DR — Delivery / process | C25: =COUNTIF(Requirements_RTM!$B$2:$B$142,"DR") | D25: =COUNTIFS(Requirements_RTM!$B$2:$B$142,"DR",Requirements_RTM!$E$2:$E$142,"M")
B26: Total | C26: =SUM(C21:C25) | D26: =SUM(D21:D25)
B28: Requirements by status | E28: Test cases by status | H28: Tasks by status
B29: Status | C29: Count | E29: Status | F29: Count | H29: Status | I29: Count
B30: Proposed | C30: =COUNTIF(Requirements_RTM!$M$2:$M$142,"Proposed") | E30: Not Written | F30: =COUNTIF(Test_Cases!$I$2:$I$52,"Not Written") | H30: Not Started | I30: =COUNTIF(Implementation_Tasks!$G$2:$G$28,"Not Started")
B31: Approved | C31: =COUNTIF(Requirements_RTM!$M$2:$M$142,"Approved") | E31: Written | F31: =COUNTIF(Test_Cases!$I$2:$I$52,"Written") | H31: In Progress | I31: =COUNTIF(Implementation_Tasks!$G$2:$G$28,"In Progress")
B32: In Progress | C32: =COUNTIF(Requirements_RTM!$M$2:$M$142,"In Progress") | E32: Passing | F32: =COUNTIF(Test_Cases!$I$2:$I$52,"Passing") | H32: In Review | I32: =COUNTIF(Implementation_Tasks!$G$2:$G$28,"In Review")
B33: Implemented | C33: =COUNTIF(Requirements_RTM!$M$2:$M$142,"Implemented") | E33: Failing | F33: =COUNTIF(Test_Cases!$I$2:$I$52,"Failing") | H33: Done | I33: =COUNTIF(Implementation_Tasks!$G$2:$G$28,"Done")
B34: Verified | C34: =COUNTIF(Requirements_RTM!$M$2:$M$142,"Verified") | E34: Blocked | F34: =COUNTIF(Test_Cases!$I$2:$I$52,"Blocked") | H34: Blocked | I34: =COUNTIF(Implementation_Tasks!$G$2:$G$28,"Blocked")
B35: Deferred | C35: =COUNTIF(Requirements_RTM!$M$2:$M$142,"Deferred")
B36: Withdrawn | C36: =COUNTIF(Requirements_RTM!$M$2:$M$142,"Withdrawn")
B38: Traceability health checks (all should be 0)
B39: Check | C39: Value | D39: Target | E39: Result
B40: Test-verified requirements with no test case | C40: =COUNTIFS(Requirements_RTM!$I$2:$I$142,"*T*",Requirements_RTM!$J$2:$J$142,"",Requirements_RTM!$E$2:$E$142,"<>W") | D40: 0 | E40: =IF(C40=D40,"PASS","FIX")
B41: Requirements (not Won't) with no implementation task | C41: =COUNTIFS(Requirements_RTM!$K$2:$K$142,"",Requirements_RTM!$E$2:$E$142,"<>W") | D41: 0 | E41: =IF(C41=D41,"PASS","FIX")
B42: Requirements with no acceptance criteria | C42: =COUNTIFS(Requirements_RTM!$H$2:$H$142,"") | D42: 0 | E42: =IF(C42=D42,"PASS","FIX")
B43: PRD sections with a coverage GAP | C43: =COUNTIF(PRD_Coverage!$E$2:$E$20,"GAP") | D43: 0 | E43: =IF(C43=D43,"PASS","FIX")
B44: Fare calculator mismatches | C44: =COUNTIF(Fare_Calculator!$N$12:$N$21,"MISMATCH") | D44: 0 | E44: =IF(C44=D44,"PASS","FIX")
B45: Zone distance asymmetries | C45: =Zones_Distances!D27 | D45: 0 | E45: =IF(C45=D45,"PASS","FIX")

Sheet Requirements_RTM
A1: Req ID | B1: Type | C1: Module | D1: Requirement statement | E1: Priority (MoSCoW) | F1: PRD § | G1: SRS § | H1: Acceptance criteria | I1: Verification (T/D/I) | J1: Test IDs | K1: Task IDs | L1: Feature branch(es) | M1: Status | N1: Evidence (commit / PR / test run) | O1: Notes | P1: PRD key (helper)
A2: FR-AUTH-01 | B2: FR | C2: AUTH | D2: The system shall let a new passenger sign up with full name, phone number, e-mail, password and an optional self-declared gender (FEMALE, MALE or PREFER_NOT_TO_SAY; default PREFER_NOT_TO_SAY). | E2: M | F2: 3 | G2: 4.1 | H2: Valid input creates a PASSENGER account and a TeslaPay wallet with ৳0 balance. A duplicate e-mail or phone returns 409 and no account is created. A password shorter than 8 characters returns 400. | I2: T | J2: TC-31, TC-50 | K2: T-08 | L2: feature/passenger-auth | M2: Implemented | N2: POST /api/auth/signup; test/auth/sign-up.test.ts — feature/passenger-auth | P2: =","&SUBSTITUTE(F2," ","")&","
A3: FR-AUTH-02 | B3: FR | C3: AUTH | D3: The system shall let passengers and drivers sign in with e-mail (or phone) and password. | E3: M | F3: 3 | G3: 4.1 | H3: Correct credentials give an authenticated session that identifies the user and role. Wrong credentials return 401 with a generic message that does not reveal whether the account exists. | I3: T | J3: TC-32 | K3: T-08 | L3: feature/passenger-auth | M3: Implemented | N3: POST /api/auth/login (e-mail or phone); test/auth/sessions.test.ts — feature/passenger-auth | P3: =","&SUBSTITUTE(F3," ","")&","
A4: FR-AUTH-03 | B4: FR | C4: AUTH | D4: The system shall let a signed-in user sign out, which invalidates the client session. | E4: M | F4: 3 | G4: 4.1 | H4: After sign-out, protected endpoints return 401 for that session. | I4: T | J4: TC-32 | K4: T-08 | L4: feature/passenger-auth | M4: Implemented | N4: POST /api/auth/logout revokes the session — feature/passenger-auth | P4: =","&SUBSTITUTE(F4," ","")&","
A5: FR-AUTH-04 | B5: FR | C5: AUTH | D5: The system shall expose the current user's profile and role to the frontend. | E5: M | F5: 3 | G5: 4.1 | H5: GET /me returns id, name and role (plus the vehicle, for drivers). Without a session it returns 401. | I5: T | J5: TC-32 | K5: T-08 | L5: feature/passenger-auth | M5: Implemented | N5: GET /api/auth/me (vehicle for drivers) — feature/passenger-auth | P5: =","&SUBSTITUTE(F5," ","")&","
A6: FR-AUTH-05 | B6: FR | C6: AUTH | D6: The frontend shall route users to the dashboard for their role and block access to the other role's pages. | E6: M | F6: 3 | G6: 4.1 | H6: A passenger who opens a driver URL is redirected or sees 403. The API enforces the same rule (NFR-SEC-03). | I6: T, D | J6: TC-04 | K6: T-09, T-19 | L6: feature/passenger-auth, feature/passenger-ui | M6: In Progress | N6: API role guards done (test/auth/access.test.ts); web routing in feature/passenger-ui — feature/passenger-auth | P6: =","&SUBSTITUTE(F6," ","")&","
A7: FR-AUTH-06 | B7: FR | C7: AUTH | D7: Driver accounts, each linked to exactly one Tesla, shall be provisioned by seed data. | E7: M | F7: 3, 6 | G7: 4.1 | H7: After seeding, Jashim can sign in and sees Bullet (capacity 3). | I7: T | J7: TC-37 | K7: T-07 | L7: feature/db-schema | M7: Implemented | N7: Jashim/Bullet and Kamal/Toofan seeded — feature/db-schema | P7: =","&SUBSTITUTE(F7," ","")&","
A8: FR-AUTH-07 | B8: FR | C8: AUTH | D8: The system may allow driver self-registration with vehicle details. | E8: W | F8: 3 | G8: 4.1 | H8: Not in MVP (A-05). | I8: — | M8: Deferred | P8: =","&SUBSTITUTE(F8," ","")&","
A9: FR-PAX-01 | B9: FR | C9: PAX | D9: The system shall provide the list of supported zones for pickup and destination selection. | E9: M | F9: 4 | G9: 4.2 | H9: GET /zones returns every seeded zone with code, name and coordinates. The UI offers only these zones. | I9: T | J9: TC-35 | K9: T-11 | L9: feature/zones-fares | M9: Implemented | N9: GET /api/zones; test/zones/zones.test.ts — feature/zones-fares | P9: =","&SUBSTITUTE(F9," ","")&","
A10: FR-PAX-02 | B10: FR | C10: PAX | D10: The system shall show a fare estimate for a pickup, destination and seat count before the passenger confirms. The estimate shall show both the solo fare and the "if pooled" fare. | E10: M | F10: 3, 5 | G10: 4.2 | H10: For Nusrat (Banani→Mohakhali, 1 seat), the estimate shows ৳75.00 solo and ৳66.00 if pooled, with the breakdown shown (BR-10). | I10: T | J10: TC-35 | K10: T-11, T-20 | L10: feature/zones-fares, feature/passenger-ui | M10: In Progress | N10: POST /api/fares/estimate returns solo and pooled (TC-35); form in feature/passenger-ui — feature/zones-fares | P10: =","&SUBSTITUTE(F10," ","")&","
A11: FR-PAX-03 | B11: FR | C11: PAX | D11: A passenger shall be able to create a ride request with pickup zone, destination zone, seats (1 to the maximum vehicle capacity), pool opt-in (default: yes), same-gender co-riders only (default: no) and payment method (CASH or TESLAPAY). | E11: M | F11: 3 | G11: 4.2 | H11: Valid input creates a request in REQUESTED status and records an audit entry. Pickup equal to destination returns 400. Seats outside the valid range return 400. An unknown zone returns 400. | I11: T | J11: TC-24, TC-33, TC-50 | K11: T-13 | L11: feature/ride-request | M11: Implemented | N11: POST /api/rides; test/rides/request.test.ts (TC-33) — feature/ride-request | P11: =","&SUBSTITUTE(F11," ","")&","
A12: FR-PAX-04 | B12: FR | C12: PAX | D12: The system shall reject a new request while the passenger already has an active request. | E12: M | F12: 3, 12 | G12: 4.2 | H12: A second request returns 409 ACTIVE_REQUEST_EXISTS. This is enforced at database level as well (NFR-CON-04). | I12: T | J12: TC-18 | K12: T-13 | L12: feature/ride-request | M12: Implemented | N12: 409 ACTIVE_REQUEST_EXISTS with the existing ride id; double submit covered (TC-18) — feature/ride-request | P12: =","&SUBSTITUTE(F12," ","")&","
A13: FR-PAX-05 | B13: FR | C13: PAX | D13: When TeslaPay is selected, the system shall reject the request if the wallet balance is lower than the estimated solo fare. | E13: S | F13: 5 | G13: 4.2 | H13: With a balance of ৳50 and a solo fare of ৳75, the request is rejected with 422 INSUFFICIENT_BALANCE. | I13: T | J13: TC-28 | K13: T-13 | L13: feature/ride-request | M13: Implemented | N13: 422 INSUFFICIENT_BALANCE against the solo estimate; Rafiq test — feature/ride-request | P13: =","&SUBSTITUTE(F13," ","")&","
A14: FR-PAX-06 | B14: FR | C14: PAX | D14: The passenger shall be able to view their current ride: status, status timeline, pickup and destination, seats, fare (estimate or locked), payment method, driver name, Tesla name and plate once matched, whether the ride is shared, and the number of co-riders. | E14: M | F14: 2, 3 | G14: 4.2 | H14: Nusrat sees "Shared ride · 1 co-rider" and only her own fare. No other passenger's name, fare or destination appears anywhere in her API responses (A-09). | I14: T, D | J14: TC-13 | K14: T-13, T-20 | L14: feature/ride-request, feature/passenger-ui | M14: In Progress | N14: GET /api/rides?scope=active and /:id with driver, Tesla, co-rider count, badge — feature/ride-request; screen in feature/passenger-ui | P14: =","&SUBSTITUTE(F14," ","")&","
A15: FR-PAX-07 | B15: FR | C15: PAX | D15: The passenger's ride view shall refresh status automatically without a manual page reload. | E15: M | F15: 3 | G15: 4.2 | H15: A status change made by the driver appears for the passenger within 5 s (polling, A-11). | I15: D | J15: TC-41 | K15: T-20 | L15: feature/passenger-ui | M15: Proposed | P15: =","&SUBSTITUTE(F15," ","")&","
A16: FR-PAX-08 | B16: FR | C16: PAX | D16: A passenger shall be able to cancel their own request when the cancellation rules allow it (BR-07). If a fee applies, the fee shall be shown and confirmed before cancelling. | E16: M | F16: 3, 12 | G16: 4.2 | H16: Cancelling in REQUESTED or MATCHED is free. Cancelling in DRIVER_ARRIVED shows "৳20.00 cancellation fee" and requires confirmation. Cancelling in STARTED, COMPLETED, CANCELLED or EXPIRED returns 409 INVALID_STATE_TRANSITION. | I16: T | J16: TC-05 | K16: T-13, T-20 | L16: feature/ride-request, feature/passenger-ui | M16: In Progress | N16: POST /api/rides/:id/cancel: REQUESTED free, STARTED/terminal 409 — feature/ride-request; MATCHED and DRIVER_ARRIVED (fee) later | P16: =","&SUBSTITUTE(F16," ","")&","
A17: FR-PAX-09 | B17: FR | C17: PAX | D17: The passenger shall be able to view their ride history (newest first, paginated), showing date, route, seats, final status, final fare, payment method and whether the ride was shared. | E17: M | F17: 3 | G17: 4.2 | H17: The history contains only the passenger's own requests. An empty history shows an empty state. | I17: T, D | J17: TC-39 | K17: T-13, T-21 | L17: feature/ride-request, feature/passenger-ui | M17: In Progress | N17: GET /api/rides?scope=history, newest first, cursor paging (TC-39) — feature/ride-request; screen in feature/passenger-ui | P17: =","&SUBSTITUTE(F17," ","")&","
A18: FR-PAX-10 | B18: FR | C18: PAX | D18: The passenger shall be able to open a past ride and see its full status timeline and fare breakdown. | E18: S | F18: 2, 3 | G18: 4.2 | H18: The timeline lists every transition with its timestamp, taken from the audit trail. | I18: T, D | J18: TC-39 | K18: T-13, T-21 | L18: feature/ride-request, feature/passenger-ui | M18: In Progress | N18: GET /api/rides/:id timeline from status_history — feature/ride-request; screen in feature/passenger-ui | P18: =","&SUBSTITUTE(F18," ","")&","
A19: FR-PAX-11 | B19: FR | C19: PAX | D19: A passenger whose declared gender is FEMALE or MALE may request a same-gender ride (co-riders of their gender only). The option shall be unavailable to passengers who declared PREFER_NOT_TO_SAY, and it requires pool opt-in. The ride view shall show a "Women-only ride" / "Men-only ride" badge. | E19: S | F19: 2, 3 | G19: 4.2 | H19: Shirin (FEMALE) can set the option. A PREFER_NOT_TO_SAY passenger setting it gets 400 VALIDATION_ERROR, as does setting it with pool opt-in = false. No co-rider gender is ever returned by passenger APIs. | I19: T | J19: TC-50 | K19: T-13, T-20 | L19: feature/ride-request, feature/passenger-ui | M19: In Progress | N19: Option validation (TC-50 parts 2-3) — feature/ride-request; matching in feature/tesla-pooling, badge in the UI | O19: Added in SRS v0.3 | P19: =","&SUBSTITUTE(F19," ","")&","
A20: FR-DRV-01 | B20: FR | C20: DRV | D20: A signed-in driver shall see their Tesla's name, plate and seat capacity. | E20: M | F20: 3 | G20: 4.3 | H20: Jashim sees "Bullet · DHAKA-TESLA-11 · 3 seats". | I20: T, D | J20: TC-40 | K20: T-14, T-22 | L20: feature/tesla-pooling, feature/driver-ui | M20: Proposed | P20: =","&SUBSTITUTE(F20," ","")&","
A21: FR-DRV-02 | B21: FR | C21: DRV | D21: A driver shall be able to go online, selecting their current zone, and go offline. | E21: M | F21: 3 | G21: 4.3 | H21: Going online sets the driver ONLINE in the chosen zone. Going offline sets OFFLINE. Both are audited. | I21: T | J21: TC-22 | K21: T-14, T-22 | L21: feature/tesla-pooling, feature/driver-ui | M21: Proposed | P21: =","&SUBSTITUTE(F21," ","")&","
A22: FR-DRV-03 | B22: FR | C22: DRV | D22: The system shall prevent a driver from going offline while they have an active pool. | E22: M | F22: 3 | G22: 4.3 | H22: Returns 409 ACTIVE_POOL_EXISTS. The UI disables the toggle and explains why. | I22: T | J22: TC-22 | K22: T-14 | L22: feature/tesla-pooling | M22: Proposed | P22: =","&SUBSTITUTE(F22," ","")&","
A23: FR-DRV-04 | B23: FR | C23: DRV | D23: An online driver shall see relevant requests. With no active pool, these are REQUESTED, non-expired requests whose pickup zone is the driver's current zone and whose seats are at most the vehicle capacity. With an OPEN pool, these are only requests compatible with that pool (BR-02). Each shows pickup, destination, seats, pool opt-in, estimated fare and age. | E23: M | F23: 3, 4 | G23: 4.3 | H23: With Jashim online in Banani and Nusrat's request pending, the list contains Nusrat. After accepting Nusrat, it contains Rafiq (compatible) and does not contain a Banani→Uttara request. An offline driver gets 409 DRIVER_OFFLINE. | I23: T | J23: TC-23 | K23: T-14, T-22 | L23: feature/tesla-pooling, feature/driver-ui | M23: Proposed | P23: =","&SUBSTITUTE(F23," ","")&","
A24: FR-DRV-05 | B24: FR | C24: DRV | D24: A driver shall be able to accept a relevant request. If the driver has no active pool, a new pool is created. If the driver has an OPEN pool, the request is added to it. | E24: M | F24: 3 | G24: 4.3 | H24: The request moves to MATCHED and becomes a pool member, and occupied seats go up by its seat count, all in one transaction. The server re-checks every rule (BR-01…BR-05) at accept time. A rule violation returns 409 or 422 with a specific code. | I24: T | J24: TC-25 | K24: T-15 | L24: feature/tesla-pooling | M24: Proposed | P24: =","&SUBSTITUTE(F24," ","")&","
A25: FR-DRV-06 | B25: FR | C25: DRV | D25: The driver shall see the active pool: status, occupied and free seats, and for each member the passenger's name, pickup, destination, seats, status, payment method and fare, plus a badge when the pool is gender-restricted. | E25: M | F25: 2, 3 | G25: 4.3 | H25: With Nusrat and Rafiq matched, Jashim sees "2 / 3 seats occupied" and both members with their fares. | I25: T, D | J25: TC-25, TC-47 | K25: T-17, T-22 | L25: feature/driver-flow, feature/driver-ui | M25: Proposed | P25: =","&SUBSTITUTE(F25," ","")&","
A26: FR-DRV-07 | B26: FR | C26: DRV | D26: The driver shall be able to mark the pool as arrived at the pickup zone. | E26: M | F26: 3 | G26: 4.3 | H26: The pool moves OPEN→DRIVER_ARRIVED, and every MATCHED member moves to DRIVER_ARRIVED. | I26: T | J26: TC-25 | K26: T-17, T-22 | L26: feature/driver-flow, feature/driver-ui | M26: Proposed | P26: =","&SUBSTITUTE(F26," ","")&","
A27: FR-DRV-08 | B27: FR | C27: DRV | D27: The driver shall be able to start the trip. | E27: M | F27: 3 | G27: 4.3 | H27: The pool moves DRIVER_ARRIVED→STARTED, and every DRIVER_ARRIVED member moves to STARTED. Fares are locked (BR-12). Starting is rejected if the pool has no member in DRIVER_ARRIVED. | I27: T | J27: TC-25 | K27: T-17, T-22 | L27: feature/driver-flow, feature/driver-ui | M27: Proposed | P27: =","&SUBSTITUTE(F27," ","")&","
A28: FR-DRV-09 | B28: FR | C28: DRV | D28: The driver shall be able to drop off (complete) each passenger individually, in any order. | E28: M | F28: 3 | G28: 4.3 | H28: The member moves STARTED→COMPLETED and payment is settled (BR-15/BR-16). When the last member is completed, the pool automatically becomes COMPLETED and the driver's current zone is set to the last drop-off zone. | I28: T | J28: TC-25 | K28: T-17, T-22 | L28: feature/driver-flow, feature/driver-ui | M28: Proposed | P28: =","&SUBSTITUTE(F28," ","")&","
A29: FR-DRV-10 | B29: FR | C29: DRV | D29: For cash payments, the driver shall be able to mark cash as collected. | E29: M | F29: 5 | G29: 4.3 | H29: The payment status for that member becomes PAID with method CASH. This action is audited. | I29: T | J29: TC-27 | K29: T-18, T-22 | L29: feature/teslapay-wallet, feature/driver-ui | M29: Proposed | P29: =","&SUBSTITUTE(F29," ","")&","
A30: FR-DRV-11 | B30: FR | C30: DRV | D30: The driver shall be able to cancel the pool before the trip starts. | E30: M | F30: 3 | G30: 4.3 | H30: The pool moves to CANCELLED. Active members move back to REQUESTED so another driver can pick them up, and passengers are not charged. Cancelling after STARTED returns 409. | I30: T | J30: TC-15 | K30: T-17, T-22 | L30: feature/driver-flow, feature/driver-ui | M30: Proposed | P30: =","&SUBSTITUTE(F30," ","")&","
A31: FR-DRV-12 | B31: FR | C31: DRV | D31: The driver shall be able to mark an arrived passenger as a no-show after a 5-minute wait. | E31: C | F31: 3 | G31: 4.3 | H31: The member moves DRIVER_ARRIVED→CANCELLED with reason NO_SHOW, and the ৳20 fee applies (BR-07). | I31: T | J31: TC-43 | K31: T-17 | L31: feature/driver-flow | M31: Proposed | P31: =","&SUBSTITUTE(F31," ","")&","
... A40: FR-POOL-08 | B40: FR | C40: POOL | D40: A pool shall be completed automatically when its last on-board member is completed. | E40: M | F40: 3 | G40: 4.4 | H40: The pool status is COMPLETED and completed_at is set. | I40: T | J40: TC-25 | K40: T-17 | L40: feature/driver-flow | M40: Proposed | P40: =","&SUBSTITUTE(F40," ","")&","
A41: FR-POOL-09 | B41: FR | C41: POOL | D41: A ride request shall belong to at most one active pool at a time. | E41: M | F41: 3 | G41: 4.4 | H41: Enforced by a unique constraint. Two drivers accepting the same request concurrently gives exactly one success; the other gets 409 INVALID_STATE_TRANSITION. | I41: T | J41: TC-06 | K41: T-06, T-15 | L41: feature/db-schema, feature/tesla-pooling | M41: In Progress | N41: pool_members_one_active_membership index tested; accept flow in feature/tesla-pooling — feature/db-schema | P41: =","&SUBSTITUTE(F41," ","")&","
A42: FR-POOL-10 | B42: FR | C42: POOL | D42: Pool membership shall be explicit and queryable. For any pool it shall be possible to list its members and each member's seats and status. | E42: M | F42: 3 | G42: 4.4 | H42: The driver's pool view and the database both show the membership. | I42: T | J42: TC-25 | K42: T-06 | L42: feature/db-schema | M42: In Progress | N42: pool_members table; roster endpoint in feature/driver-flow — feature/db-schema | P42: =","&SUBSTITUTE(F42," ","")&","
A43: FR-POOL-11 | B43: FR | C43: POOL | D43: Gender restrictions (BR-18) shall be enforced on the server at accept time, under the same pool lock as capacity. | E43: S | F43: 2, 4 | G43: 4.4 | H43: With Shirin (same-gender option) in Bullet's pool, accepting Rafiq returns 422 NOT_COMPATIBLE with reason GENDER_RESTRICTED, and accepting Nusrat succeeds. Accepting a same-gender request from Shirin into a pool containing Rafiq returns the same 422. | I43: T | J43: TC-47, TC-48, TC-51 | K43: T-15 | L43: feature/tesla-pooling | M43: Proposed | O43: Added in SRS v0.3 | P43: =","&SUBSTITUTE(F43," ","")&","
A44: FR-POOL-12 | B44: FR | C44: POOL | D44: A pool's gender restriction shall be recalculated whenever a member leaves before the trip starts. | E44: S | F44: 3 | G44: 4.4 | H44: If Shirin was the only member requesting it and she cancels, the restriction returns to NONE and Rafiq becomes acceptable. | I44: T | J44: TC-49 | K44: T-17 | L44: feature/driver-flow | M44: Proposed | O44: Added in SRS v0.3 | P44: =","&SUBSTITUTE(F44," ","")&","
A45: FR-FARE-01 | B45: FR | C45: FARE | D45: The system shall calculate each passenger's fare with the formula in BR-10, using the zone distance table (BR-09). | E45: M | F45: 5 | G45: 4.5 | H45: The worked examples in §6.4 are reproduced exactly by unit tests. | I45: T | J45: TC-03, TC-12 | K45: T-10 | L45: feature/zones-fares | M45: Implemented | N45: domain/fare.ts computeFare; test/domain/fare.test.ts (TC-03, TC-12) — feature/zones-fares | P45: =","&SUBSTITUTE(F45," ","")&","
A46: FR-FARE-02 | B46: FR | C46: FARE | D46: At request time, the system shall store and show an estimate: the solo fare, plus the pooled fare if the passenger opted in. | E46: M | F46: 5 | G46: 4.5 | H46: The request record stores estimated_fare_paisa (solo). The response includes both figures. | I46: T | J46: TC-35 | K46: T-11 | L46: feature/zones-fares | M46: Implemented | N46: Estimate endpoint (feature/zones-fares); estimated_fare_paisa stored on each request and both figures in the ride view — feature/ride-request | P46: =","&SUBSTITUTE(F46," ","")&","
A47: FR-FARE-03 | B47: FR | C47: FARE | D47: At trip start, the system shall lock each on-board member's final fare and store the rates used (base, per-km, discount rate, distance, seats, pooled flag). | E47: M | F47: 2, 5 | G47: 4.5 | H47: Changing the rate configuration afterwards does not change any locked fare. | I47: T | J47: TC-09, TC-11 | K47: T-17 | L47: feature/driver-flow | M47: Proposed | P47: =","&SUBSTITUTE(F47," ","")&","
A48: FR-FARE-04 | B48: FR | C48: FARE | D48: The passenger and driver views shall show a fare breakdown: base, distance charge, pool discount, seats and total. | E48: M | F48: 5 | G48: 4.5 | H48: The numbers in the breakdown add up to the total shown. | I48: T, D | J48: TC-35 | K48: T-11 | L48: feature/zones-fares | M48: In Progress | N48: API returns base, distance charge, discount, seats, total (TC-35); views in the UI branches — feature/zones-fares | P48: =","&SUBSTITUTE(F48," ","")&","
A49: FR-FARE-05 | B49: FR | C49: FARE | D49: A cancellation fee (BR-07) shall be recorded as its own charge linked to the request. | E49: M | F49: 5 | G49: 4.5 | H49: Rafiq cancelling after arrival creates a 2000-paisa CANCELLATION_FEE charge. | I49: T | J49: TC-14 | K49: T-13 | L49: feature/ride-request | M49: Proposed | P49: =","&SUBSTITUTE(F49," ","")&","
A50: FR-FARE-06 | B50: FR | C50: FARE | D50: All monetary values shall be stored and calculated as integer paisa. They are formatted as ৳ with two decimals only for display. | E50: M | F50: 5 | G50: 4.5 | H50: There are no floating-point money columns in the schema. 6600 is displayed as "৳66.00". | I50: T | J50: TC-45 | K50: T-06 | L50: feature/db-schema | M50: In Progress | N50: BIGINT paisa columns (feature/db-schema); integer-only fare arithmetic in domain/money.ts (feature/zones-fares); display formatting in the UI | P50: =","&SUBSTITUTE(F50," ","")&","
A51: FR-PAY-01 | B51: FR | C51: PAY | D51: Every passenger shall have one TeslaPay wallet. The passenger can see its balance and transaction list. | E51: M | F51: 5 | G51: 4.6 | H51: Nusrat's seeded balance is visible, and her transactions are listed newest first. | I51: T | J51: TC-29 | K51: T-18, T-21 | L51: feature/teslapay-wallet, feature/passenger-ui | M51: Proposed | P51: =","&SUBSTITUTE(F51," ","")&","
A52: FR-PAY-02 | B52: FR | C52: PAY | D52: The passenger shall be able to add simulated funds (top-up) of ৳50–৳5,000 per operation. | E52: S | F52: 5 | G52: 4.6 | H52: A top-up of ৳500 increases the balance by 50000 paisa and creates a TOPUP ledger entry. Out-of-range amounts return 400. The UI labels this clearly as simulated money. | I52: T | J52: TC-29 | K52: T-18, T-21 | L52: feature/teslapay-wallet, feature/passenger-ui | M52: Proposed | P52: =","&SUBSTITUTE(F52," ","")&","
A53: FR-PAY-03 | B53: FR | C53: PAY | D53: For TESLAPAY rides, completing the member shall debit the locked fare from the wallet atomically and create a RIDE_PAYMENT ledger entry. | E53: M | F53: 5 | G53: 4.6 | H53: The balance goes down by exactly the locked fare. Payment status becomes PAID. | I53: T | J53: TC-26 | K53: T-18 | L53: feature/teslapay-wallet | M53: Proposed | P53: =","&SUBSTITUTE(F53," ","")&","
A54: FR-PAY-04 | B54: FR | C54: PAY | D54: For CASH rides, completing the member shall set payment status to PENDING_CASH until the driver marks it collected (FR-DRV-10). | E54: M | F54: 5 | G54: 4.6 | H54: Rafiq's payment status shows "Cash due ৳60.00" and then "Paid (cash)". | I54: T | J54: TC-27 | K54: T-18 | L54: feature/teslapay-wallet | M54: Proposed | P54: =","&SUBSTITUTE(F54," ","")&","
A55: FR-PAY-05 | B55: FR | C55: PAY | D55: A cancellation fee shall be debited from the wallet for TESLAPAY requests. For CASH requests it shall be recorded as UNPAID. | E55: S | F55: 5 | G55: 4.6 | H55: The wallet ledger or charge record reflects the fee. Collecting unpaid cash fees is out of scope (§13.4). | I55: T | J55: TC-14 | K55: T-18 | L55: feature/teslapay-wallet | M55: Proposed | P55: =","&SUBSTITUTE(F55," ","")&","
A56: FR-PAY-06 | B56: FR | C56: PAY | D56: A wallet balance shall never go negative. Every balance change shall have exactly one ledger entry. | E56: M | F56: 5, 6 | G56: 4.6 | H56: A DB CHECK (balance ≥ 0) exists. The sum of ledger entries equals the balance for every seeded and test wallet. | I56: T | J56: TC-26 | K56: T-06, T-18 | L56: feature/db-schema, feature/teslapay-wallet | M56: In Progress | N56: wallets_balance_check + append-only ledger tested; settlement in feature/teslapay-wallet — feature/db-schema | P56: =","&SUBSTITUTE(F56," ","")&","
A57: FR-HIST-01 | B57: FR | C57: HIST | D57: Every status change of a ride request, pool or driver availability shall be recorded with entity, from-status, to-status, actor (user id and role, or SYSTEM), reason and timestamp. | E57: M | F57: 2, 6 | G57: 4.7 | H57: Each transition in §5 creates exactly one audit row, in the same transaction as the change. | I57: T | J57: TC-30 | K57: T-12 | L57: feature/ride-request | M57: In Progress | N57: recordTransition in the same transaction: ride create, cancel, expiry — feature/ride-request; pool and driver transitions follow | P57: =","&SUBSTITUTE(F57," ","")&","
A58: FR-HIST-02 | B58: FR | C58: HIST | D58: Audit records shall be append-only. The application shall provide no update or delete path for them. | E58: M | F58: 2 | G58: 4.7 | H58: There is no endpoint or service method that modifies audit rows. | I58: I, T | J58: TC-30 | K58: T-06, T-12 | L58: feature/db-schema, feature/ride-request | M58: Implemented | N58: Append-only trigger (feature/db-schema); audit module has no update/delete path — feature/ride-request | P58: =","&SUBSTITUTE(F58," ","")&","
A59: FR-HIST-03 | B59: FR | C59: HIST | D59: Rejected transition attempts shall be logged (in application logs, not the audit table) with the actor and the reason. | E59: S | F59: 6 | G59: 4.7 | H59: An invalid "start" call produces a WARN log entry with the request id. | I59: T | J59: TC-39 | K59: T-12 | L59: feature/ride-request | M59: Implemented | N59: error-handler logs 409/422 at WARN as command.rejected with code and request id — feature/ride-request | P59: =","&SUBSTITUTE(F59," ","")&","
A60: FR-HIST-04 | B60: FR | C60: HIST | D60: A completed or cancelled ride shall keep enough data to explain later who rode, in which Tesla, with how many seats, when each status changed, what was charged and why, and how it was paid. | E60: M | F60: 2 | G60: 4.7 | H60: An operator can reconstruct the complete Nusrat and Rafiq ride (scenario E1) from database records alone. | I60: T | J60: TC-30 | K60: T-13 | L60: feature/ride-request | M60: In Progress | N60: Ride, timeline and fare rows readable per ride — feature/ride-request; full E1 reconstruction after feature/teslapay-wallet | P60: =","&SUBSTITUTE(F60," ","")&","
A61: BR-01 | B61: BR | C61: RULES | D61: Capacity. A request may be accepted into a pool only if occupied_seats + request.seats ≤ vehicle.capacity. The database enforces this as well (NFR-CON-01). | E61: M | F61: 3, 12 | G61: 6.1 | H61: Verified by the linked test cases (see SRS §6). | I61: T | J61: TC-01 | K61: T-15 | L61: feature/tesla-pooling | M61: Proposed | P61: =","&SUBSTITUTE(F61," ","")&","
A62: BR-02 | B62: BR | C62: RULES | D62: Compatibility (matching rule). A REQUESTED request R may join an OPEN pool P only if all of the following hold: (a) R.pickup_zone = P.pickup_zone; (b) R and every active member of P opted in to pooling; (c) for every active member M of P, R.destination = M.destination or the two destinations are adjacent zones (BR-08); (d) R was created no more than 10 minutes after P was created; (e) BR-01 holds; (f) the gender rule BR-18 holds. | E62: M | F62: 4 | G62: 6.1 | H62: Verified by the linked test cases (see SRS §6). | I62: T | J62: TC-20, TC-47 | K62: T-15 | L62: feature/tesla-pooling | M62: Proposed | P62: =","&SUBSTITUTE(F62," ","")&","
A63: BR-03 | B63: BR | C63: RULES | D63: Solo pools. The first request accepted by a driver always creates a new pool, provided its seats ≤ capacity. If that request did not opt in to pooling, the pool is private (FR-POOL-04). | E63: M | F63: 3 | G63: 6.1 | H63: Verified by the linked test cases (see SRS §6). | I63: T | J63: TC-20 | K63: T-15 | L63: feature/tesla-pooling | M63: Proposed | P63: =","&SUBSTITUTE(F63," ","")&","
A64: BR-04 | B64: BR | C64: RULES | D64: One active pool per driver. A driver may have at most one active pool. | E64: M | F64: 3 | G64: 6.1 | H64: Verified by the linked test cases (see SRS §6). | I64: T | J64: TC-19 | K64: T-15 | L64: feature/tesla-pooling | M64: Proposed | P64: =","&SUBSTITUTE(F64," ","")&","
A65: BR-05 | B65: BR | C65: RULES | D65: One active request per passenger. A passenger may have at most one active request. | E65: M | F65: 3 | G65: 6.1 | H65: Verified by the linked test cases (see SRS §6). | I65: T | J65: TC-18 | K65: T-13 | L65: feature/ride-request | M65: Implemented | N65: Service check plus partial unique index; TC-18 — feature/ride-request | P65: =","&SUBSTITUTE(F65," ","")&","
A66: BR-06 | B66: BR | C66: RULES | D66: Closed state machines. Only the transitions in §5 are allowed, and only by the listed actor. All others are rejected without side effects. | E66: M | F66: 3, 12 | G66: 6.1 | H66: Verified by the linked test cases (see SRS §6). | I66: T | J66: TC-02, TC-08 | K66: T-12 | L66: feature/ride-request | M66: Implemented | N66: domain/state-machine.ts over shared transition tables; TC-08 exhaustive — feature/ride-request | P66: =","&SUBSTITUTE(F66," ","")&","
A67: BR-08 | B67: BR | C67: RULES | D67: Zones. The zone list, the distance table and the adjacency list are fixed reference data (seeded, §13.3). Distances are symmetric road-approximation values in kilometres, stored as integer metres. Adjacency is symmetric and declared explicitly; it is not derived from distance. | E67: M | F67: 4 | G67: 6.1 | H67: Verified by the linked test cases (see SRS §6). | I67: I, T | J67: TC-20, TC-37 | K67: T-07 | L67: feature/db-schema | M67: Implemented | N67: prisma/seed-data/zones.ts; symmetry test — feature/db-schema | P67: =","&SUBSTITUTE(F67," ","")&","
A68: BR-07 | B68: BR | C68: RULES | D68: Passenger cancellation. In REQUESTED or MATCHED it is free. In DRIVER_ARRIVED it is allowed with a ৳20 (2000 paisa) fee. In STARTED it is not allowed; the passenger is dropped off instead. After a terminal state it is not allowed. Driver no-show cancellation (C) is allowed ≥ 5 min after arrival and has the same fee. Driver pool cancellation is allowed only before STARTED, costs passengers nothing, and returns them to REQUESTED. | E68: M | F68: 3, 12 | G68: 6.2 | H68: Verified by the linked test cases (see SRS §6). | I68: T | J68: TC-05, TC-15 | K68: T-13 | L68: feature/ride-request | M68: In Progress | N68: domain/cancellation.ts policy (FREE/FEE/FORBIDDEN); fee charging in feature/driver-flow — feature/ride-request | P68: =","&SUBSTITUTE(F68," ","")&","
A69: BR-09 | B69: BR | C69: RULES | D69: Distance. distance_m is the zone-to-zone table value for the request's pickup and destination (e.g. Banani→Mohakhali = 3000 m). Each passenger is charged for their own pickup→destination distance, not for any detour. | E69: M | F69: 4, 5 | G69: 6.3 | H69: Verified by the linked test cases (see SRS §6). | I69: T | J69: TC-03, TC-12 | K69: T-10 | L69: feature/zones-fares | M69: Implemented | N69: zones.service distanceBetween from the seeded table (TC-12) — feature/zones-fares | P69: =","&SUBSTITUTE(F69," ","")&","
A70: BR-10 | B70: BR | C70: RULES | D70: Formula (per seat). distanceCharge = roundHalfUp(distance_m × PER_KM_PAISA / 1000); poolDiscount = pooled ? roundHalfUp(distanceCharge × POOL_DISCOUNT_BPS / 10000) : 0; farePerSeat = BASE_FARE_PAISA + distanceCharge − poolDiscount; passengerFare = farePerSeat × seats. | E70: M | F70: 5 | G70: 6.3 | H70: Verified by the linked test cases (see SRS §6). | I70: T | J70: TC-03, TC-10, TC-12 | K70: T-10 | L70: feature/zones-fares | M70: Implemented | N70: domain/fare.ts; TC-03, TC-10, TC-12 — feature/zones-fares | P70: =","&SUBSTITUTE(F70," ","")&","
A71: BR-11 | B71: BR | C71: RULES | D71: Rates (MVP defaults, configurable). BASE_FARE_PAISA = 3000 (৳30), PER_KM_PAISA = 1500 (৳15/km), POOL_DISCOUNT_BPS = 2000 (20 % of the distance charge), CANCELLATION_FEE_PAISA = 2000 (৳20). The base fare is never discounted. | E71: M | F71: 5 | G71: 6.3 | H71: Verified by the linked test cases (see SRS §6). | I71: T | J71: TC-03 | K71: T-10 | L71: feature/zones-fares | M71: Implemented | N71: FARE_* env rates via config/rules.ts CURRENT_FARE_RATES; base never discounted (test) — feature/zones-fares | P71: =","&SUBSTITUTE(F71," ","")&","
A72: BR-12 | B72: BR | C72: RULES | D72: Locking. The estimate is shown at request time. The final fare is fixed at trip start. pooled = true only if two or more distinct passengers' requests move to STARTED together in that pool. One passenger booking two seats does not count as pooling. The fare and the rates used are stored immutably. | E72: M | F72: 5 | G72: 6.3 | H72: Verified by the linked test cases (see SRS §6). | I72: T | J72: TC-09, TC-10 | K72: T-10 | L72: feature/zones-fares | M72: In Progress | N72: computeFare takes the pooled flag (TC-10: 2 seats of 1 passenger not pooled); locking at start in feature/driver-flow — feature/zones-fares | P72: =","&SUBSTITUTE(F72," ","")&","
A73: BR-13 | B73: BR | C73: RULES | D73: Rounding. Half-up to a whole paisa, applied only where BR-10 says. With the default rates and whole-100 m distances, every result is exact. | E73: M | F73: 5 | G73: 6.3 | H73: Verified by the linked test cases (see SRS §6). | I73: T | J73: TC-03 | K73: T-10 | L73: feature/zones-fares | M73: Implemented | N73: roundHalfUpDiv on the integer remainder; test/domain/money.test.ts — feature/zones-fares | P73: =","&SUBSTITUTE(F73," ","")&","
A74: BR-14 | B74: BR | C74: RULES | D74: Money storage. Integer paisa in 64-bit integer columns. There is no floating point anywhere in money logic (D-05). | E74: M | F74: 5 | G74: 6.3 | H74: Verified by the linked test cases (see SRS §6). | I74: I, T | J74: TC-45 | K74: T-06 | L74: feature/db-schema | M74: Implemented | N74: BIGINT *_paisa columns; db/money.ts exact conversion — feature/db-schema | P74: =","&SUBSTITUTE(F74," ","")&","
A75: BR-15 | B75: BR | C75: RULES | D75: TeslaPay settlement. When a member is completed, the locked fare is debited in the same transaction as the COMPLETED transition. If the balance is insufficient at that moment (A-14), the payment status becomes PENDING_CASH and the driver collects cash. | E75: M | F75: 5 | G75: 6.5 | H75: Verified by the linked test cases (see SRS §6). | I75: T | J75: TC-26 | K75: T-18 | L75: feature/teslapay-wallet | M75: Proposed | P75: =","&SUBSTITUTE(F75," ","")&","
A76: BR-16 | B76: BR | C76: RULES | D76: Cash settlement. The payment is PENDING_CASH on completion and becomes PAID when the driver marks it collected. | E76: M | F76: 5 | G76: 6.5 | H76: Verified by the linked test cases (see SRS §6). | I76: T | J76: TC-27 | K76: T-18 | L76: feature/teslapay-wallet | M76: Proposed | P76: =","&SUBSTITUTE(F76," ","")&","
A77: BR-17 | B77: BR | C77: RULES | D77: Top-up. Simulated only, ৳50–৳5,000 per operation, credited immediately. | E77: M | F77: 5 | G77: 6.5 | H77: Verified by the linked test cases (see SRS §6). | I77: T | J77: TC-29 | K77: T-18 | L77: feature/teslapay-wallet | M77: Proposed | P77: =","&SUBSTITUTE(F77," ","")&","
A78: BR-18 | B78: BR | C78: RULES | D78: Same-gender rides. Let G(x) be a passenger's declared gender. A pool's restriction is FEMALE_ONLY or MALE_ONLY if any active member requested a same-gender ride, and NONE otherwise. Request R may join pool P only if: (a) when P is restricted, G(R) matches the restriction; and (b) when R requests a same-gender ride, every active member of P has gender G(R). Passengers with PREFER_NOT_TO_SAY can join only unrestricted pools. The driver's gender is not considered. The fare rules are unchanged (BR-10…12). | E78: M | F78: 2, 4 | G78: 6.1 | H78: Verified by the linked test cases (see SRS §6). | I78: T | J78: TC-47, TC-48, TC-49, TC-51 | K78: T-15 | L78: feature/tesla-pooling | M78: Proposed | O78: Added in SRS v0.3 | P78: =","&SUBSTITUTE(F78," ","")&","
A79: NFR-SEC-01 | B79: NFR | C79: SEC | D79: Passwords shall be stored only as salted, adaptive hashes (bcrypt cost ≥ 10 or argon2id). | E79: M | F79: 6 | G79: 9.1 | H79: No plaintext or reversible password exists in the database or logs. | I79: I, T | J79: TC-44 | K79: T-08 | L79: feature/passenger-auth | M79: Implemented | N79: bcrypt (cost 12; 4 in tests); TC-44 — feature/passenger-auth | P79: =","&SUBSTITUTE(F79," ","")&","
A80: NFR-SEC-02 | B80: NFR | C80: SEC | D80: Every endpoint except sign-up, sign-in, zones (optional) and health shall require authentication. | E80: M | F80: 6 | G80: 9.1 | H80: Unauthenticated calls return 401. | I80: T | J80: TC-32 | K80: T-08 | L80: feature/passenger-auth | M80: In Progress | N80: requireAuth in place; applied to each new endpoint as modules arrive — feature/passenger-auth | P80: =","&SUBSTITUTE(F80," ","")&","
A81: NFR-SEC-03 | B81: NFR | C81: SEC | D81: Object-level authorization: a passenger may read or change only their own requests and wallet. A driver may act only on their own pool and on requests shown to them as relevant. Role checks apply to every endpoint. | E81: M | F81: 2, 6, 12 | G81: 9.1 | H81: Rafiq cancelling Nusrat's ride returns 404/403 and nothing changes. Nusrat calling a driver endpoint returns 403. This is covered by automated tests. | I81: T | J81: TC-04, TC-13 | K81: T-09 | L81: feature/passenger-auth | M81: In Progress | N81: Role guards (feature/passenger-auth); rides scoped to their owner, 404 for others (TC-04 part) — feature/ride-request | P81: =","&SUBSTITUTE(F81," ","")&","
A82: NFR-SEC-04 | B82: NFR | C82: SEC | D82: All input shall be validated against a schema at the API boundary (types, ranges, enums, unknown fields rejected). | E82: M | F82: 6 | G82: 9.1 | H82: Invalid payloads return 400 VALIDATION_ERROR with field details. | I82: T | J82: TC-33 | K82: T-04 | L82: feature/project-setup | M82: In Progress | N82: validateBody with strict shared schemas for auth, estimates and rides; list query parsed with Zod — feature/ride-request | P82: =","&SUBSTITUTE(F82," ","")&","
A83: NFR-SEC-05 | B83: NFR | C83: SEC | D83: Secrets shall come only from environment variables. .env.example has placeholders only, and no real secret is committed. | E83: M | F83: 6, 16 | G83: 9.1 | H83: The repository scan finds no secrets, and .env is git-ignored. | I83: I | J83: TC-34 | K83: T-05 | L83: feature/project-setup | M83: Implemented | N83: .gitignore excludes .env; .env.example placeholders only — commits f221565, 7d59b8d | P83: =","&SUBSTITUTE(F83," ","")&","
A84: NFR-SEC-06 | B84: NFR | C84: SEC | D84: Session tokens shall be protected: an httpOnly, SameSite cookie (Secure in production), or a short-lived bearer token. CORS is restricted to the frontend origin. Standard security headers are set. | E84: M | F84: 6 | G84: 9.1 | H84: Inspection of headers and cookie flags passes. | I84: I | J84: TC-06, TC-07 | K84: T-04, T-08 | L84: feature/project-setup, feature/passenger-auth | M84: Implemented | N84: httpOnly SameSite=Lax cookie (Secure via COOKIE_SECURE), helmet, CORS — feature/passenger-auth | P84: =","&SUBSTITUTE(F84," ","")&","
A85: NFR-SEC-07 | B85: NFR | C85: SEC | D85: Authentication endpoints shall be rate-limited per IP. | E85: S | F85: 12 | G85: 9.1 | H85: More than 10 login attempts per minute from one IP returns 429. | I85: T | J85: TC-38 | K85: T-09 | L85: feature/passenger-auth | M85: Implemented | N85: express-rate-limit 10/min per IP; TC-38 — feature/passenger-auth | P85: =","&SUBSTITUTE(F85," ","")&","
A86: NFR-SEC-08 | B86: NFR | C86: SEC | D86: Database access shall use parameterised queries or an ORM only. | E86: M | F86: 6 | G86: 9.1 | H86: No string-concatenated SQL appears in the code. | I86: I | J86: TC-06 | K86: T-04 | L86: feature/project-setup | M86: In Progress | N86: Prisma query API + tagged $queryRaw only — feature/db-schema | P86: =","&SUBSTITUTE(F86," ","")&","
A87: NFR-SEC-09 | B87: NFR | C87: SEC | D87: Error responses shall not leak stack traces or internal details in production. | E87: M | F87: 6 | G87: 9.1 | H87: A 500 response contains only the code, a generic message and the requestId. | I87: T | J87: TC-34 | K87: T-04 | L87: feature/project-setup | M87: Implemented | N87: Generic INTERNAL_ERROR message; details only in logs — commit 51da796 | P87: =","&SUBSTITUTE(F87," ","")&","
A88: NFR-CON-01 | B88: NFR | C88: CON | D88: Last-seat race. When Bullet has 1 free seat and two accept operations for different 1-seat requests (Nusrat's and Shirin's) run concurrently, exactly one shall succeed. The other returns 409 CAPACITY_EXCEEDED, and occupied seats never exceed capacity. | E88: M | F88: 12 | G88: 9.2 | H88: An automated test fires both accepts in parallel N times (N ≥ 20). Every run has exactly one success, and the DB CHECK is never violated. | I88: T | J88: TC-06, TC-07 | K88: T-15, T-16 | L88: feature/tesla-pooling | M88: Proposed | P88: =","&SUBSTITUTE(F88," ","")&","
A89: NFR-CON-02 | B89: NFR | C89: CON | D89: Every state transition shall be an atomic compare-and-set on the current status (e.g. update … where status = expected), inside a DB transaction together with all its side effects (membership, seats, fare, payment, audit). | E89: M | F89: 6, 12 | G89: 9.2 | H89: A crash or error mid-operation leaves no partial state. Two concurrent transitions on the same entity give one success and one 409. | I89: T | J89: TC-06, TC-17 | K89: T-12, T-16 | L89: feature/ride-request, feature/tesla-pooling | M89: In Progress | N89: CAS on status for cancel and expiry, audit in the same transaction — feature/ride-request; accept/pool moves in feature/tesla-pooling | P89: =","&SUBSTITUTE(F89," ","")&","
A90: NFR-CON-03 | B90: NFR | C90: CON | D90: Seat claims shall be serialised per pool (row-level lock on the pool, or a conditional increment guarded by the capacity CHECK). The chosen mechanism shall be documented in the README together with what would change at larger scale. | E90: M | F90: 12 | G90: 9.2 | H90: The README section "Concurrency" exists and matches the code. | I90: I, T | J90: TC-06 | K90: T-15 | L90: feature/tesla-pooling | M90: Proposed | N90: Mechanism designed: ARCHITECTURE.md §7, ADR-0006 | P90: =","&SUBSTITUTE(F90," ","")&","
A91: NFR-CON-04 | B91: NFR | C91: CON | D91: "One active request per passenger", "one active pool per driver" and "a request is in at most one active pool" shall be enforced by database constraints, in addition to service checks. | E91: M | F91: 6, 12 | G91: 9.2 | H91: Direct concurrent inserts cannot create duplicates. | I91: T | J91: TC-18, TC-19 | K91: T-06, T-15 | L91: feature/db-schema, feature/tesla-pooling | M91: Implemented | N91: Partial unique indexes; test/db/constraints.test.ts — feature/db-schema | P91: =","&SUBSTITUTE(F91," ","")&","
A92: NFR-CON-05 | B92: NFR | C92: CON | D92: Wallet debits and credits shall be atomic with their ledger entry. The balance can never go negative. | E92: M | F92: 5, 6 | G92: 9.2 | H92: Concurrent debit tests leave balance = Σ ledger and balance ≥ 0. | I92: T | J92: TC-26 | K92: T-18 | L92: feature/teslapay-wallet | M92: Proposed | P92: =","&SUBSTITUTE(F92," ","")&","
A93: NFR-CON-06 | B93: NFR | C93: CON | D93: Request creation should be idempotent for client retries (an Idempotency-Key header, or reliance on NFR-CON-04). | E93: C | F93: 12 | G93: 9.2 | H93: A retried POST with the same key returns the original request. | I93: T | J93: TC-18 | K93: T-13 | L93: feature/ride-request | M93: Implemented | N93: Relies on NFR-CON-04: a retry gets 409 ACTIVE_REQUEST_EXISTS with the original ride id — feature/ride-request | P93: =","&SUBSTITUTE(F93," ","")&","
A94: NFR-REL-01 | B94: NFR | C94: REL | D94: All API errors shall use the standard error format (§8.2), with a correlation requestId. | E94: M | F94: 6 | G94: 9.3 | H94: Contract tests check the error shape. | I94: T | J94: TC-34 | K94: T-04 | L94: feature/project-setup | M94: Implemented | N94: middleware/error-handler.ts; test/app.test.ts — commit 51da796 | P94: =","&SUBSTITUTE(F94," ","")&","
A95: NFR-REL-02 | B95: NFR | C95: REL | D95: GET /health shall report API liveness and DB connectivity. Docker health checks shall use it, and the database container shall have its own health check. | E95: M | F95: 6 | G95: 9.3 | H95: docker compose ps shows the services as healthy. The API starts only after the DB is healthy. | I95: D, I | J95: TC-36 | K95: T-05 | L95: feature/project-setup | M95: Implemented | N95: /health + compose health checks — commits 51da796, 7d59b8d | P95: =","&SUBSTITUTE(F95," ","")&","
A96: NFR-REL-03 | B96: NFR | C96: REL | D96: If the database is unreachable, the API shall return 503 and recover automatically when the DB returns, with no restart needed. | E96: S | F96: 6 | G96: 9.3 | H96: Manual test: stop the DB, call the API (503), start the DB, call the API (200). | I96: D | J96: TC-42 | K96: T-05 | L96: feature/project-setup | M96: Proposed | P96: =","&SUBSTITUTE(F96," ","")&","
A97: NFR-REL-04 | B97: NFR | C97: REL | D97: Request expiry (RT-04) shall be applied reliably even if no scheduler has run: expired requests shall never be accepted and shall show as EXPIRED on read. | E97: M | F97: 3 | G97: 9.3 | H97: Accepting a request older than 15 min returns 409, whether or not the sweeper has run. | I97: T | J97: TC-24 | K97: T-13 | L97: feature/ride-request | M97: In Progress | N97: Expiry on read and before every passenger command, plus the 60 s sweep — feature/ride-request; accept check in feature/tesla-pooling | P97: =","&SUBSTITUTE(F97," ","")&","
A98: NFR-PERF-01 | B98: NFR | C98: PERF | D98: With seed-scale data on the local Docker setup, 95 % of API requests shall complete in under 300 ms. | E98: S | F98: 6 | G98: 9.4 | H98: A simple load script (e.g. 20 concurrent users for 1 min) meets p95 < 300 ms. | I98: T (load script) | J98: TC-46 | K98: T-23 | L98: pre-release | M98: Proposed | P98: =","&SUBSTITUTE(F98," ","")&","
A99: NFR-PERF-02 | B99: NFR | C99: PERF | D99: The indexes listed in §7 shall exist, so that request lists, history and pool lookups do not need full table scans. | E99: M | F99: 6 | G99: 9.4 | H99: Migration inspection and EXPLAIN on key queries. | I99: I | J99: TC-41 | K99: T-06 | L99: feature/db-schema | M99: Implemented | N99: Indexes in init + integrity migrations (ERD §5) — feature/db-schema | P99: =","&SUBSTITUTE(F99," ","")&","
A100: NFR-PERF-03 | B100: NFR | C100: PERF | D100: The client polling interval shall be 3–5 s, and polling shall stop when a ride reaches a terminal state or the tab is hidden. | E100: S | F100: 3 | G100: 9.4 | H100: Inspection of network activity. | I100: I | J100: TC-41 | K100: T-20 | L100: feature/passenger-ui | M100: Proposed | P100: =","&SUBSTITUTE(F100," ","")&","
A101: NFR-USA-01 | B101: NFR | C101: USA | D101: Every data-driven view shall have explicit loading, empty and error states, and an error state shall offer a retry. | E101: M | F101: 6 | G101: 9.5 | H101: Review of every screen in §8.1. | I101: D, I | J101: TC-41 | K101: T-19 | L101: feature/passenger-ui | M101: Proposed | P101: =","&SUBSTITUTE(F101," ","")&","
A102: NFR-USA-02 | B102: NFR | C102: USA | D102: Statuses shall be shown with human-readable labels (e.g. STARTED = "On the way") and a progress stepper or timeline. | E102: M | F102: 3, 6 | G102: 9.5 | H102: Visual check. | I102: D, I | J102: TC-41 | K102: T-20 | L102: feature/passenger-ui | M102: Proposed | P102: =","&SUBSTITUTE(F102," ","")&","
A103: NFR-USA-03 | B103: NFR | C103: USA | D103: Action buttons shall appear only when the transition is valid for the current state and role. The server remains authoritative (BR-06). | E103: M | F103: 3 | G103: 9.5 | H103: A driver in OPEN sees "Arrived" but not "Start". | I103: D, I | J103: TC-41 | K103: T-20, T-22 | L103: feature/passenger-ui, feature/driver-ui | M103: Proposed | P103: =","&SUBSTITUTE(F103," ","")&","
A104: NFR-USA-04 | B104: NFR | C104: USA | D104: Money shall be displayed as ৳ with exactly two decimals. The fare breakdown shall be one tap or click away. | E104: M | F104: 5 | G104: 9.5 | H104: "৳66.00" is shown for 6600 paisa. | I104: D, I | J104: TC-41 | K104: T-20 | L104: feature/passenger-ui | M104: Proposed | P104: =","&SUBSTITUTE(F104," ","")&","
A105: NFR-USA-05 | B105: NFR | C105: USA | D105: The UI shall be usable on a 360 px-wide mobile viewport and via keyboard, with labelled form controls and sufficient contrast. | E105: S | F105: 6 | G105: 9.5 | H105: Manual check at mobile width; lint or axe shows no critical issues. | I105: D, I | J105: TC-41 | K105: T-19 | L105: feature/passenger-ui | M105: Proposed | P105: =","&SUBSTITUTE(F105," ","")&","
A106: NFR-USA-06 | B106: NFR | C106: USA | D106: Destructive actions (cancel ride, cancel pool) shall ask for confirmation and state any fee. | E106: M | F106: 3 | G106: 9.5 | H106: Visual check. | I106: D, I | J106: TC-41 | K106: T-20, T-22 | L106: feature/passenger-ui, feature/driver-ui | M106: Proposed | P106: =","&SUBSTITUTE(F106," ","")&","
A107: NFR-POR-01 | B107: NFR | C107: POR | D107: docker compose up, run on a clean machine with only Docker installed, shall start the database, API and web app, apply migrations and load seed data, with no manual steps beyond copying .env.example to .env. | E107: M | F107: 6 | G107: 9.6 | H107: Tested from a fresh clone. The reference personas can sign in. | I107: D | J107: TC-36 | K107: T-05 | L107: feature/project-setup | M107: Implemented | N107: Fresh volume: migrate deploy → seed → API healthy; web healthy — feature/db-schema | P107: =","&SUBSTITUTE(F107," ","")&","
A108: NFR-POR-02 | B108: NFR | C108: POR | D108: All configuration (DB URL, secrets, rates, CORS origin, ports) shall be via environment variables with documented defaults. | E108: M | F108: 6 | G108: 9.6 | H108: .env.example lists every variable. | I108: I | K108: T-05 | L108: feature/project-setup | M108: Implemented | N108: config/env.ts, config/rules.ts, .env.example — commits 9ddba2e, 51da796, 7d59b8d | P108: =","&SUBSTITUTE(F108," ","")&","
...

Sheet Test_Cases
A1: Test ID | B1: Title | C1: Req IDs | D1: Type | E1: PRD §12 area | F1: Preconditions (reference personas) | G1: Steps | H1: Expected result | I1: Status | J1: Test file / evidence | K1: Last run
A2: TC-01 | B2: Bullet's capacity can never be exceeded | C2: FR-POOL-02, BR-01 | D2: Integration | E2: #1 Capacity | F2: Jashim online in Banani; Bullet (3 seats) has an OPEN pool with 3 occupied seats; Shirin has a 1-seat REQUESTED ride. Second run: 2 seats occupied, a compatible 2-seat request. | G2: 1) Jashim accepts Shirin's request. 2) Reset to 2 occupied; Jashim accepts the 2-seat request. | H2: Both accepts return 409 CAPACITY_EXCEEDED; occupied_seats unchanged; no pool_member row created; requests stay REQUESTED. | I2: Not Written
A3: TC-02 | B3: Invalid state transitions are rejected without side effects | C3: BR-06, FR-POOL-05 | D3: Integration | E3: #2 Transitions | F3: Pool P OPEN with Nusrat MATCHED; a second pool P2 STARTED with Rafiq STARTED. | G3: 1) POST /pools/P/start. 2) Complete Nusrat while MATCHED. 3) Nusrat cancels after P2-style STARTED. 4) Accept a request into STARTED P2. 5) Arrive on a COMPLETED pool. | H3: Each returns 409 (INVALID_STATE_TRANSITION / POOL_NOT_OPEN); statuses, seats, fares and status_history unchanged. | I3: Written | J3: Ride level in test/rides/cancel.test.ts and test/domain/state-machine.test.ts; pool moves later | K3: 2026-09-24 partial
A4: TC-03 | B4: Nusrat's and Rafiq's pooled fares calculate correctly | C4: FR-FARE-01, BR-09, BR-10, BR-11, BR-13 | D4: Unit | E4: #3 Fares | F4: Default rates: base 3000, per km 1500, discount 2000 bps. | G4: Call fare(distance=3000m, seats=1, pooled=true/false) and fare(2500m, 1, true/false). | H4: Nusrat pooled 6600 / solo 7500; Rafiq pooled 6000 / solo 6750 paisa; breakdown components add up to total. | I4: Passing | J4: apps/api/test/domain/fare.test.ts | K4: 2026-09-24 passing (local + Docker)
A5: TC-04 | B5: Users can't modify or view another user's ride | C5: NFR-SEC-03, FR-AUTH-05 | D5: Integration | E5: #4 Authorization | F5: Nusrat has an active ride R; Jashim owns pool P; Kamal is online. | G5: 1) Rafiq GET/cancel R. 2) Nusrat calls POST /driver/requests/:id/accept. 3) Kamal POST /pools/P/arrive, /start, member complete. | H5: 1) 404 NOT_FOUND, R unchanged. 2) 403 FORBIDDEN. 3) 404/403 and P unchanged. | I5: Written | J5: Roles in test/auth/access.test.ts; ride ownership in test/rides/read.test.ts and cancel.test.ts; pools later | K5: 2026-09-24 partial
A6: TC-05 | B6: Cancellation rules hold | C6: BR-07, FR-PAX-08 | D6: Integration | E6: #5 Cancellation | F6: Rides for Nusrat in REQUESTED, MATCHED, DRIVER_ARRIVED and STARTED (separate setups). | G6: Nusrat cancels in each state. | H6: REQUESTED/MATCHED: CANCELLED, no charge. DRIVER_ARRIVED: CANCELLED with 2000-paisa fee. STARTED: 409 INVALID_STATE_TRANSITION. | I6: Written | J6: REQUESTED and STARTED in test/rides/cancel.test.ts, policy in test/domain/cancellation.test.ts; MATCHED and DRIVER_ARRIVED later | K6: 2026-09-24 partial
A7: TC-06 | B7: Concurrent claims can't corrupt pool capacity (last seat) | C7: NFR-CON-01, NFR-CON-02, NFR-CON-03, FR-POOL-09 | D7: Integration | E7: #6 Concurrency | F7: Bullet has 2/3 seats occupied; Nusrat and Shirin each have a compatible 1-seat REQUESTED ride. Second scenario: Jashim and Kamal both online in Banani, one open request. | G7: 1) Fire accept(Nusrat) and accept(Shirin) in parallel (Promise.all), repeat ≥20 times with fresh data. 2) Jashim and Kamal accept the same request in parallel. | H7: Every run: exactly one 200 and one 409; occupied_seats = 3 max; no CHECK violation. Scenario 2: one success, request in exactly one pool. | I7: Not Written
A8: TC-07 | B8: Database CHECK prevents over-capacity even bypassing the service | C8: FR-POOL-02, NFR-CON-01 | D8: Integration | E8: #1 Capacity | F8: Pool for Bullet with occupied_seats = 3. | G8: Direct SQL update occupied_seats = 4. | H8: Database rejects with CHECK constraint violation. | I8: Passing | J8: apps/api/test/db/constraints.test.ts | K8: 2026-09-24 passing (local + Docker)
A9: TC-08 | B9: Transition table is exhaustive (unit) | C9: BR-06, NFR-MNT-02 | D9: Unit | E9: #2 Transitions | F9: Pure canTransition(entity, from, to, actorRole). | G9: Iterate all (from, to, actor) combinations for ride request and pool. | H9: Only RT-01…RT-11 / PT-01…PT-06 are allowed; everything else is rejected. | I9: Passing | J9: apps/api/test/domain/state-machine.test.ts | K9: 2026-09-24 passing (local + Docker)
A10: TC-09 | B10: Fare locks at trip start; discount only if actually shared | C10: BR-12, FR-FARE-03 | D10: Integration | E10: #3 Fares | F10: Nusrat and Rafiq MATCHED in Bullet's pool. | G10: A) Arrive, start, check fares. B) Rafiq cancels before start, then arrive and start. | H10: A) Nusrat 6600, Rafiq 6000, pooled=true, rates snapshot stored. B) Nusrat 7500, pooled=false. | I10: Not Written
A11: TC-10 | B11: Multi-seat booking by one passenger is not pooling | C11: BR-12, BR-10 | D11: Unit | E11: #3 Fares | F11: Nusrat requests 2 seats Banani→Mohakhali alone. | G11: Start trip and compute fare. | H11: 15000 paisa (7500 × 2), pooled=false. | I11: Passing | J11: apps/api/test/domain/fare.test.ts (fare level); trip-start check with feature/driver-flow | K11: 2026-09-24 passing (local + Docker)
A12: TC-11 | B12: Locked fare is immutable after rate change | C12: FR-FARE-03 | D12: Integration | E12: #3 Fares | F12: Nusrat's fare locked at 6600. | G12: Change PER_KM_PAISA config to 2000 and re-read ride. | H12: Locked fare still 6600 with original rate snapshot. | I12: Not Written
A13: TC-12 | B13: Shirin's fares and zone distance lookup | C13: BR-09, BR-10, FR-FARE-01 | D13: Unit | E13: #3 Fares | F13: Zone table seeded. | G13: fare(Banani→Tejgaon, 1 seat, pooled / solo). | H13: Distance 5000 m; pooled 9000, solo 10500. | I13: Passing | J13: apps/api/test/domain/fare.test.ts, test/zones/zones.test.ts, test/fares/estimate.test.ts | K13: 2026-09-24 passing (local + Docker)
A14: TC-13 | B14: Passenger never sees co-rider personal data or fares | C14: FR-PAX-06, NFR-SEC-03 | D14: Integration | E14: #4 Authorization | F14: Nusrat and Rafiq in the same pool. | G14: Nusrat GET /rides/:id and /rides?scope=active. | H14: Response shows shared=true, coRiders=1, own fare only; no Rafiq name, destination or fare in the payload. | I14: Not Written
A15: TC-14 | B15: Cancellation fee recorded and debited | C15: FR-FARE-05, FR-PAY-05 | D15: Integration | E15: #5 Cancellation | F15: Nusrat (TeslaPay) and Rafiq (Cash) in DRIVER_ARRIVED. | G15: Both cancel. | H15: Nusrat: CANCELLATION_FEE charge 2000 + wallet ledger −2000. Rafiq: charge 2000 with payment status UNPAID. | I15: Not Written
A16: TC-15 | B16: Driver cancels pool before start; rejected after start | C16: FR-DRV-11, BR-07 | D16: Integration | E16: #5 Cancellation | F16: Pool with Nusrat and Rafiq in MATCHED; another pool STARTED. | G16: Jashim cancels the first pool; then tries to cancel the STARTED pool. | H16: First: pool CANCELLED, Nusrat & Rafiq back to REQUESTED, no charges. Second: 409. | I16: Not Written
A17: TC-16 | B17: Seats freed on cancel; pool auto-cancels when empty | C17: FR-POOL-06, FR-POOL-07 | D17: Integration | E17: #1 Capacity | F17: Pool with Nusrat and Rafiq (2/3). | G17: Rafiq cancels; then Nusrat cancels. | H17: After Rafiq: occupied 1. After Nusrat: pool CANCELLED (reason ALL_MEMBERS_CANCELLED); Jashim free to accept. | I17: Not Written
A18: TC-17 | B18: Concurrent passenger cancel vs driver accept | C18: NFR-CON-02 | D18: Integration | E18: #6 Concurrency | F18: Shirin REQUESTED; Jashim OPEN pool compatible. | G18: Run Shirin cancel and Jashim accept in parallel, ≥20 times. | H18: Exactly one wins; final state is either CANCELLED with no membership or MATCHED with membership — never both. | I18: Not Written
A19: TC-18 | B19: One active request per passenger (incl. double submit / retry) | C19: FR-PAX-04, BR-05, NFR-CON-04, NFR-CON-06 | D19: Integration | E19: #6 Concurrency | F19: Nusrat has no active ride. | G19: Submit two ride requests in parallel; then a third sequentially; then retry the first POST with the same Idempotency-Key (if implemented). | H19: Exactly one created; others 409 ACTIVE_REQUEST_EXISTS; idempotent retry returns the original request. | I19: Passing | J19: apps/api/test/rides/request.test.ts (no Idempotency-Key: retries rely on the unique index) | K19: 2026-09-24 passing (local + Docker)
A20: TC-19 | B20: One active pool per driver | C20: BR-04, NFR-CON-04 | D20: Integration | E20: #1 Capacity | F20: Jashim has an OPEN pool with a private (non-opt-in) request. | G20: Jashim accepts an unrelated request. | H20: 422 NOT_COMPATIBLE / 409; no second pool row for Jashim. | I20: Not Written
A21: TC-20 | B21: Matching rule: compatible vs incompatible requests | C21: BR-02, BR-03, BR-08, FR-POOL-03, FR-POOL-04 | D21: Unit | E21: Matching (PRD §4) | F21: Pool P from Banani with Nusrat → Mohakhali (opt-in). | G21: Check isCompatible for: Rafiq→Gulshan 1; Shirin→Tejgaon; Banani→Uttara; Gulshan 1→Mohakhali pickup; Rafiq opt-in=false; request 11 min after P created. | H21: Compatible: Rafiq, Shirin. Not compatible: Uttara, different pickup, opt-out, >10 min. API accept of an incompatible one returns 422. | I21: Not Written
A22: TC-21 | B22: Members can join only while pool OPEN | C22: FR-POOL-05 | D22: Integration | E22: #2 Transitions | F22: Pool DRIVER_ARRIVED with Nusrat; Rafiq REQUESTED compatible. | G22: Jashim accepts Rafiq. | H22: 409 POOL_NOT_OPEN. | I22: Not Written
A23: TC-22 | B23: Driver availability rules | C23: FR-DRV-02, FR-DRV-03 | D23: Integration | E23: Driver flow | F23: Jashim offline; later with active pool. | G23: Go online in Banani; go offline with active pool; go offline after completion. | H23: Online OK and audited; offline with active pool 409 ACTIVE_POOL_EXISTS; offline after completion OK. | I23: Not Written
A24: TC-23 | B24: Relevant request feed for Jashim | C24: FR-DRV-04 | D24: Integration | E24: Driver flow | F24: Requests: Nusrat (BAN→MHK), Rafiq (BAN→GL1), X (BAN→UTR), Y (GL1→MHK). Jashim online in Banani. | G24: GET /driver/requests before and after accepting Nusrat; also while offline. | H24: Before: Nusrat, Rafiq, X (not Y). After: Rafiq only (+ Shirin if present). Offline: 409 DRIVER_OFFLINE. | I24: Not Written
A25: TC-24 | B25: Expired requests can't be accepted | C25: NFR-REL-04, FR-PAX-03 | D25: Integration | E25: #2 Transitions | F25: Shirin's request requested_at = now − 16 min, sweeper not run. | G25: Jashim accepts; Shirin reads her ride. | H25: Accept 409; ride shows EXPIRED. | I25: Written | J25: Read side in test/rides/read.test.ts; the accept part with feature/tesla-pooling | K25: 2026-09-24 partial
A26: TC-25 | B26: Happy path: Nusrat and Rafiq share Bullet end to end | C26: FR-DRV-05, FR-DRV-06, FR-DRV-07, FR-DRV-08, FR-DRV-09, FR-POOL-01, FR-POOL-08, FR-POOL-10 | D26: E2E | E26: Scenario E1 | F26: Seeded personas; Jashim online in Banani. | G26: Nusrat requests; Rafiq requests; Jashim accepts both; arrive; start; drop Nusrat at Mohakhali; drop Rafiq at Gulshan 1. | H26: Statuses follow §5; pool shows 2/3 seats; Nusrat COMPLETED before Rafiq; pool auto-COMPLETED; Jashim's zone = Gulshan 1. | I26: Not Written
A27: TC-26 | B27: TeslaPay settlement and ledger integrity | C27: FR-PAY-03, FR-PAY-06, BR-15, NFR-CON-05 | D27: Integration | E27: Payment | F27: Nusrat wallet 50000 paisa, TeslaPay, pooled trip. | G27: Complete Nusrat. | H27: Balance 43400; RIDE_PAYMENT −6600 ledger row; balance = Σ ledger; payment PAID. | I27: Not Written
A28: TC-27 | B28: Cash payment pending then collected | C28: FR-PAY-04, FR-DRV-10, BR-16 | D28: Integration | E28: Payment | F28: Rafiq pays cash, pooled trip. | G28: Complete Rafiq; Jashim marks cash collected. | H28: PENDING_CASH 6000 → PAID; audited. | I28: Not Written
A29: TC-28 | B29: Insufficient TeslaPay balance at request | C29: FR-PAX-05 | D29: Integration | E29: Payment | F29: Shirin wallet 5000 paisa; solo estimate 10500. | G29: Shirin requests with TESLAPAY. | H29: 422 INSUFFICIENT_BALANCE; no ride created. | I29: Not Written
A30: TC-29 | B30: Wallet top-up limits | C30: FR-PAY-01, FR-PAY-02, BR-17 | D30: Integration | E30: Payment | F30: Nusrat wallet. | G30: Top up ৳500, ৳10, ৳6000. | H30: ৳500 credited (+50000, TOPUP row); ৳10 and ৳6000 → 400. | I30: Not Written
A31: TC-30 | B31: Audit trail fully reconstructs the ride | C31: FR-HIST-01, FR-HIST-02, FR-HIST-04 | D31: Integration | E31: History | F31: Run TC-25. | G31: Query status_history for Nusrat's ride and the pool. | H31: One row per transition with actor, role, reason, timestamp; no update/delete path exists; ride reconstructable from records. | I31: Not Written
A32: TC-31 | B32: Passenger sign-up validation | C32: FR-AUTH-01 | D32: Integration | E32: Auth | F32: Nusrat already exists. | G32: Sign up new passenger; duplicate e-mail; 6-char password. | H32: 201 + wallet ৳0; 409; 400. | I32: Passing | J32: apps/api/test/auth/sign-up.test.ts | K32: 2026-09-24 passing (local + Docker)
A33: TC-32 | B33: Sign-in, sign-out and /me | C33: FR-AUTH-02, FR-AUTH-03, FR-AUTH-04, NFR-SEC-02 | D33: Integration | E33: Auth | F33: Seeded Jashim. | G33: Login ok; login wrong password; /me; logout; /me again; call protected endpoint without session. | H33: 200 with role DRIVER + vehicle; 401 generic; 401 after logout; 401 unauthenticated. | I33: Passing | J33: apps/api/test/auth/sessions.test.ts | K33: 2026-09-24 passing (local + Docker)
A34: TC-33 | B34: Input validation at the API boundary | C34: FR-PAX-03, NFR-SEC-04 | D34: Integration | E34: Validation | F34: Nusrat signed in. | G34: Create ride with pickup = destination; seats 0; seats 4; unknown zone; extra field. | H34: 400 VALIDATION_ERROR with field details each time. | I34: Passing | J34: apps/api/test/rides/request.test.ts | K34: 2026-09-24 passing (local + Docker)
A35: TC-34 | B35: Standard error format and no leaks | C35: NFR-REL-01, NFR-SEC-09 | D35: Integration | E35: Errors | F35: Production mode. | G35: Trigger 400, 404, 409 and a forced 500. | H35: Body {error:{code,message,details},requestId}; 500 has no stack trace. | I35: Written | J35: apps/api/test/app.test.ts (404, malformed JSON, requestId); 409/500 cases added with later modules | K35: 2026-09-24 passing
A36: TC-35 | B36: Zones list and fare estimate (solo & pooled with breakdown) | C36: FR-PAX-01, FR-PAX-02, FR-FARE-02, FR-FARE-04 | D36: Integration | E36: #3 Fares | F36: Nusrat signed in; zones seeded. | G36: GET /zones; POST /fares/estimate BAN→MHK 1 seat. | H36: 10 zones with code/name/coords; estimate solo 7500, pooled 6600, breakdown base/distance/discount. | I36: Passing | J36: apps/api/test/zones/zones.test.ts, apps/api/test/fares/estimate.test.ts | K36: 2026-09-24 passing (local + Docker)
A37: TC-36 | B37: docker compose up on a fresh clone | C37: NFR-POR-01, NFR-REL-02, DR-09 | D37: Manual | E37: Docker | F37: Clean machine with Docker only. | G37: Clone; cp .env.example .env; docker compose up. | H37: All services healthy; migrations + seed applied; Nusrat and Jashim can sign in. | I37: Not Written
A38: TC-37 | B38: Seed is idempotent and uses the reference personas | C38: NFR-POR-03, DR-15, FR-AUTH-06, BR-08 | D38: Manual | E38: Docker | F38: Stack running. | G38: Run seed twice; search repo for user1/driver1. | H38: No duplicates or errors; personas present; no placeholders found. | I38: Passing | J38: apps/api/test/db/seed.test.ts (automated; no user1/driver1 in seed data) | K38: 2026-09-24 passing (local + Docker)
A39: TC-38 | B39: Login rate limiting | C39: NFR-SEC-07 | D39: Integration | E39: Security | F39: — | G39: 11 failed logins within 1 minute from one IP. | H39: 11th returns 429 RATE_LIMITED. | I39: Passing | J39: apps/api/test/auth/rate-limit.test.ts | K39: 2026-09-24 passing (local + Docker)
A40: TC-39 | B40: Passenger history and ride detail | C40: FR-PAX-09, FR-PAX-10, FR-HIST-03 | D40: Integration | E40: History | F40: Nusrat has 2 past rides; Rafiq has 1. | G40: Nusrat GET /rides?scope=history and a detail. | H40: Only Nusrat's rides, newest first, with timeline and fare breakdown. | I40: Passing | J40: apps/api/test/rides/read.test.ts | K40: 2026-09-24 passing (local + Docker)
A41: TC-40 | B41: Driver sees Tesla, pool and history | C41: FR-DRV-01, FR-DRV-13 | D41: Integration | E41: Driver flow | F41: Jashim with 1 completed pool; Kamal with 1. | G41: Jashim GET dashboard and /driver/pools?scope=history. | H41: Bullet · DHAKA-TESLA-11 · 3 seats; only Jashim's pools. | I41: Not Written
A42: TC-41 | B42: UI states and usability walkthrough | C42: NFR-USA-01, NFR-USA-02, NFR-USA-03, NFR-USA-04, NFR-USA-05, NFR-USA-06, FR-PAX-07 | D42: Manual | E42: Frontend | F42: Running app; mobile viewport 360 px. | G42: Walk through every screen in SRS §8.1 incl. slow network, empty data, API down. | H42: Loading/empty/error states present; labels human-readable; only valid actions shown; ৳ with 2 decimals; confirmations state fees; status refreshes ≤5 s. | I42: Not Written
A43: TC-42 | B43: Database outage returns 503 and recovers | C43: NFR-REL-03 | D43: Manual | E43: Reliability | F43: Stack running. | G43: Stop DB container; call API; start DB; call API. | H43: 503 SERVICE_UNAVAILABLE, then 200 without API restart. | I43: Not Written
A44: TC-43 | B44: Driver marks no-show after 5 minutes | C44: FR-DRV-12 | D44: Integration | E44: #5 Cancellation | F44: Pool DRIVER_ARRIVED 6 min ago with Shirin. | G44: Jashim marks Shirin no-show; repeat at 2 min. | H44: 6 min: CANCELLED reason NO_SHOW + 2000 fee. 2 min: 409. | I44: Not Written
A45: TC-44 | B45: Passwords are hashed | C45: NFR-SEC-01 | D45: Inspection | E45: Security | F45: Seeded DB. | G45: Inspect users.password_hash and logs. | H45: Only bcrypt/argon2 hashes; no plaintext anywhere. | I45: Passing | J45: apps/api/test/auth/sessions.test.ts (automated: bcrypt hashes, SHA-256 token hash) | K45: 2026-09-24 passing
A46: TC-45 | B46: Money is integer paisa everywhere | C46: FR-FARE-06, BR-14 | D46: Inspection | E46: #3 Fares | F46: Migrations. | G46: Inspect all money columns and fare code. | H46: BIGINT/INTEGER columns only; no float arithmetic on money. | I46: Not Written
A47: TC-46 | B47: Performance smoke test | C47: NFR-PERF-01 | D47: Manual | E47: Performance | F47: Seeded Docker stack. | G47: Load script: 20 virtual users for 60 s on key endpoints. | H47: p95 < 300 ms; no errors. | I47: Not Written
A48: TC-47 | B48: Same-gender pool rejects a rider of another gender | C48: FR-POOL-11, BR-18, BR-02, FR-DRV-06 | D48: Integration | E48: Matching (PRD §4) | F48: Shirin (FEMALE, same-gender option) accepted into Bullet's pool; Rafiq (MALE) and Nusrat (FEMALE) have compatible REQUESTED rides. | G48: 1) Check pool restriction. 2) Jashim accepts Rafiq. 3) Jashim accepts Nusrat. | H48: 1) FEMALE_ONLY and driver view shows the badge. 2) 422 NOT_COMPATIBLE, reason GENDER_RESTRICTED; nothing changes. 3) 200; pool 2/3. | I48: Not Written
A49: TC-48 | B49: Same-gender request cannot join a mixed pool | C49: FR-POOL-11, BR-18 | D49: Integration | E49: Matching (PRD §4) | F49: Rafiq (MALE) in Bullet's pool (restriction NONE). Shirin (FEMALE) requests with the same-gender option. A PREFER_NOT_TO_SAY passenger has a compatible ride. | G49: 1) Jashim accepts Shirin. 2) Make the pool FEMALE_ONLY via a new setup and accept the PREFER_NOT_TO_SAY passenger. | H49: Both rejected with 422 GENDER_RESTRICTED. | I49: Not Written
A50: TC-49 | B50: Restriction is recalculated when a member leaves | C50: FR-POOL-12, BR-18 | D50: Integration | E50: #5 Cancellation | F50: Pool FEMALE_ONLY with Shirin (option) and Nusrat (no option). | G50: Shirin cancels in MATCHED; Jashim then accepts Rafiq. | H50: Restriction becomes NONE after Shirin leaves; Rafiq accepted. | I50: Not Written
A51: TC-50 | B51: Gender and same-gender option validation and privacy | C51: FR-PAX-11, FR-AUTH-01, FR-PAX-03 | D51: Integration | E51: Validation | F51: New sign-ups; Nusrat and Rafiq in one pool. | G51: 1) Sign up without gender. 2) PREFER_NOT_TO_SAY passenger requests with the option. 3) Option with pool opt-in = false. 4) Inspect Nusrat's ride response and Jashim's pool response. | H51: 1) 201 with PREFER_NOT_TO_SAY. 2) and 3) 400 VALIDATION_ERROR. 4) No co-rider or member gender field present; only the restriction badge. | I51: Written | J51: Parts 1-3 in test/auth/sign-up.test.ts and test/rides/request.test.ts; passenger side of part 4 in test/rides/read.test.ts; driver pool response later | K51: 2026-09-24 partial
A52: TC-51 | B52: Concurrent accepts cannot create a mixed restricted pool | C52: FR-POOL-11, BR-18, NFR-CON-02 | D52: Integration | E52: #6 Concurrency | F52: Empty OPEN pool for Bullet after Nusrat (no option) accepted; Shirin (option) and Rafiq request concurrently. | G52: Fire accept(Shirin) and accept(Rafiq) in parallel, ≥20 times with fresh data. | H52: Never both accepted: either the pool is FEMALE_ONLY with Shirin, or NONE with Rafiq and Shirin rejected. | I52: Not Written

Sheet Assumptions_Decisions
A1: ID | B1: Kind | C1: Statement | D1: Rationale / resolution | E1: Alternatives considered | F1: Related reqs | G1: Status | H1: Date | I1: Notes / who confirmed
A2: A-01 | B2: Assumption | C2: Geography is a fixed list of 10 Dhaka zones with a hand-authored, symmetric distance table and an adjacency list (§13.3). | D2: PRD §4 says not to fight map APIs. It is also deterministic and hand-checkable. | F2: BR-08, BR-09 | G2: Proposed | H2: 2026-09-23
A3: A-02 | B3: Assumption | C3: A passenger's pickup is the zone itself. There is no street address or pin. | D3: Keeps pooling pickup to a single stop. | F3: BR-02 | G3: Proposed | H3: 2026-09-23
A4: A-03 | B4: Assumption | C4: A driver owns exactly one Tesla, and its capacity is fixed (Bullet = 3). | D4: PRD §3 says "own a Tesla with fixed capacity". | F4: FR-DRV-01, BR-01 | G4: Proposed | H4: 2026-09-23
A5: A-04 | B5: Assumption | C5: A passenger may book 1 to capacity seats for companions without accounts. The fare is per seat. | D5: Common real-world case; PRD says "seats". | F5: FR-PAX-03, BR-10 | G5: Proposed | H5: 2026-09-23
A6: A-05 | B6: Assumption | C6: Drivers and their Teslas are seeded. There is no driver self-sign-up or KYC. | D6: PRD lists only "sign in" for drivers. | F6: FR-AUTH-06, FR-AUTH-07 | G6: Proposed | H6: 2026-09-23
A7: A-06 | B7: Assumption | C7: Each person has one role. A user cannot be both passenger and driver. | D7: Simplifies authorization. | F7: NFR-SEC-03 | G7: Proposed | H7: 2026-09-23
A8: A-07 | B8: Assumption | C8: Pooling is opt-in per request, and the default is on. | D8: PRD says "when it makes sense". Privacy-minded passengers can opt out. | F8: FR-POOL-04, BR-02 | G8: Proposed | H8: 2026-09-23
A9: A-08 | B9: Assumption | C9: Arrival and start are pool-level, because members share the pickup zone. Drop-off is per passenger. | D9: Real trips drop riders at different points. | F9: FR-DRV-07, FR-DRV-08, FR-DRV-09 | G9: Proposed | H9: 2026-09-23
A10: A-09 | B10: Assumption | C10: A passenger sees that the ride is shared and the number of co-riders, but not their names, destinations or fares. | D10: PRD §2: "their own fare and status, not anyone else's". | F10: FR-PAX-06 | G10: Proposed | H10: 2026-09-23
A11: A-10 | B11: Assumption | C11: The driver sees each member's name, destination, seats, fare and payment method. | D11: Needed to run the trip and collect cash. | F11: FR-DRV-06 | G11: Proposed | H11: 2026-09-23
A12: A-11 | B12: Assumption | C12: Clients refresh by polling every 3–5 s. There are no WebSockets in the MVP. | D12: PRD §9: avoid complexity without a reason. Polling is enough at MVP scale. | F12: FR-PAX-07, NFR-PERF-03 | G12: Proposed | H12: 2026-09-23
A13: A-12 | B13: Assumption | C13: New members can join only while the pool is OPEN, i.e. before the driver arrives. | D13: Avoids delaying passengers who are already waiting. | F13: FR-POOL-05 | G13: Proposed | H13: 2026-09-23
... A19: A-18 | B19: Assumption | C19: Ratings, the admin console, notifications and surge pricing are out of scope. | D19: PRD lists them as optional. MVP focus. | F19: FR-AUTH-07 | G19: Proposed | H19: 2026-09-23
A20: A-19 | B20: Assumption | C20: Gender is self-declared and optional, with no verification. Misdeclaration is a known limitation. | D20: Identity verification (KYC) is out of scope (A-05, A-18). | F20: FR-AUTH-01, FR-PAX-11 | G20: Confirmed | H20: 2026-09-24 | I20: Confirmed by product owner (optional gender)
A21: A-20 | B21: Assumption | C21: Gender is personal data. It is never shown to co-riders or included in their API responses. Drivers see only the pool's restriction badge. | D21: Data minimisation (A-09, NFR-SEC-03). | F21: FR-PAX-11, NFR-SEC-03 | G21: Proposed | H21: 2026-09-24
A22: A-21 | B22: Assumption | C22: The same-gender option restricts co-riders only, not the driver. | D22: Both driver personas are male; a driver rule would make restricted rides unmatchable in the MVP. | F22: BR-18 | G22: Confirmed | H22: 2026-09-24 | I22: Confirmed by product owner (passengers only)
A23: D-01 | B23: Decision | C23: The SRS follows ISO/IEC/IEEE 29148 as Markdown in the repo, with an Excel RTM. | D23: Reviewable in git history, sits next to the code, and the industry-standard structure. | E23: Word document; Excel only | F23: DR-18 | G23: Confirmed | H23: 2026-09-23 | I23: Confirmed by product owner in SRS planning session
A24: D-02 | B24: Decision | C24: Geography is zones plus a distance table plus an adjacency list. | D24: Hand-verifiable fares and no dependency on a map service. | E24: Lat/long with haversine; a free map | F24: BR-08, BR-09 | G24: Confirmed | H24: 2026-09-23 | I24: Confirmed by product owner in SRS planning session
A25: D-03 | B25: Decision | C25: Matching uses the same pickup zone, same or adjacent destinations, and a 10-minute window. | D25: Simple, transparent and consistent, and it handles the overlapping Nusrat/Rafiq trips. | E25: Detour percentage; same pickup only | F25: BR-02 | G25: Confirmed | H25: 2026-09-23 | I25: Confirmed by product owner in SRS planning session
A26: D-04 | B26: Decision | C26: The driver accepts each request explicitly into the pool. | D26: Matches the PRD's driver flow ("accept a ride/pool") and gives the driver control. | E26: Auto-join after the first accept; full auto-dispatch | F26: FR-DRV-05, BR-03 | G26: Confirmed | H26: 2026-09-23 | I26: Confirmed by product owner in SRS planning session
A27: D-05 | B27: Decision | C27: Money is stored as integer paisa (BIGINT). | D27: Exact integer arithmetic, no float bugs in JS, and identical results in JS and SQL. | E27: DECIMAL(10,2) | F27: BR-14, FR-FARE-06 | G27: Confirmed | H27: 2026-09-23 | I27: Confirmed by product owner in SRS planning session
A28: D-06 | B28: Decision | C28: Fare = base + per-km charge − 20 % of the distance charge when pooled, per seat. | D28: Easy to check by hand, the discount scales with distance, and the base covers the pickup cost. | E28: Flat discount; split the shared leg | F28: BR-10, BR-11 | G28: Confirmed | H28: 2026-09-23 | I28: Confirmed by product owner in SRS planning session
A29: D-07 | B29: Decision | C29: The fare locks at trip start. | D29: The discount is given only when the ride really was shared, and the price is fixed during the ride. | E29: Lock at match; compute at completion | F29: BR-12, FR-FARE-03 | G29: Confirmed | H29: 2026-09-23 | I29: Confirmed by product owner in SRS planning session
A30: D-08 | B30: Decision | C30: Cancellation is free before arrival, ৳20 after arrival, and not allowed after start. | D30: Fair to both sides and discourages no-shows. | E30: Free until start; only before match | F30: BR-07 | G30: Confirmed | H30: 2026-09-23 | I30: Confirmed by product owner in SRS planning session
A31: D-09 | B31: Decision | C31: Payment is cash or the simulated TeslaPay wallet with a ledger. | D31: Covers both PRD options and shows ledger integrity. | E31: Cash only; wallet only | F31: FR-PAY-01…06 | G31: Confirmed | H31: 2026-09-23 | I31: Confirmed by product owner in SRS planning session
A32: D-10 | B32: Decision | C32: The API style is REST with action sub-resources for transitions. | D32: Simple resources, explicit guarded commands, and easy to test with curl or HTTP clients. | E32: GraphQL; RPC | F32: §8.2 | G32: Proposed | H32: 2026-09-23
A33: D-11 | B33: Decision | C33: Status updates use polling. | D33: No extra infrastructure; enough for the MVP (A-11). | E33: WebSockets, SSE | F33: FR-PAX-07 | G33: Proposed | H33: 2026-09-23
A34: D-12 | B34: Decision | C34: There are two linked state machines (ride request and pool). | D34: Pooled trips have passenger-level and trip-level events that cannot share one status. | E34: A single ride status | F34: §5, BR-06 | G34: Proposed | H34: 2026-09-23 | I34: Chosen by product owner in architecture session
A35: D-13 | B35: Decision | C35: The DBMS is PostgreSQL 16 (ADR-0002). | D35: CHECK constraints, partial unique indexes, row locks and transactional DDL directly support the integrity rules. | E35: MySQL, SQLite, MongoDB | F35: DC-03, NFR-CON-04, ADR-0002 | G35: Proposed | H35: 2026-09-23 | I35: Chosen by product owner in architecture session
A36: D-14 | B36: Decision | C36: The system is a modular monolith: Next.js web + one Express API + PostgreSQL (ADR-0001). | D36: Every invariant fits in one ACID transaction, with no distributed consistency (PRD §9). | E36: Next.js-only; microservices | F36: DC-05, DR-14 | G36: Proposed | H36: 2026-09-24 | I36: Chosen by product owner in architecture session
A37: D-15 | B37: Decision | C37: The API is built with Express 5 + TypeScript (ADR-0003). | D37: No hidden control flow, a large ecosystem, and explicit layering that is simple to trace and maintain. | E37: NestJS; Fastify | F37: DC-02, DC-07 | G37: Confirmed | H37: 2026-09-24 | I37: Chosen by product owner in architecture session
A38: D-16 | B38: Decision | C38: Data access uses Prisma, with CHECK constraints, partial unique indexes and triggers in hand-written SQL migrations (ADR-0004). | D38: Type-safe DX for most queries. Raw SQL is visible exactly where the integrity guarantees are implemented. | E38: Drizzle; Knex; TypeORM | F38: NFR-CON-04, NFR-POR-03, NFR-SEC-08 | G38: Confirmed | H38: 2026-09-24 | I38: Chosen by product owner in architecture session
A39: D-17 | B39: Decision | C39: Auth uses opaque DB-backed sessions (SHA-256 hash stored) in an httpOnly cookie, behind a same-origin Next.js /api proxy (ADR-0005). | D39: Real logout; a DB leak exposes no usable tokens; first-party cookies across different hosts. | E39: JWT in cookie; Auth.js/Lucia | F39: FR-AUTH-02, FR-AUTH-03, NFR-SEC-06 | G39: Confirmed | H39: 2026-09-24 | I39: Chosen by product owner in architecture session
A40: D-18 | B40: Decision | C40: Concurrency uses row locks in the fixed order driver → pool → ride → wallet, compare-and-set transitions and DB constraints. Expiry is checked in the accept CAS, plus a 60 s in-process sweeper (ADR-0006). | D40: Deterministic outcome for the last-seat race, with no extra infrastructure. | E40: Optimistic versioning; SERIALIZABLE; Redis lock | F40: NFR-CON-01, NFR-CON-02, NFR-CON-03, NFR-REL-04 | G40: Proposed | H40: 2026-09-24
A41: D-19 | B41: Decision | C41: The repo is an npm-workspaces monorepo: apps/web, apps/api, packages/shared (Zod, enums, transition tables) (ADR-0008). | D41: One source for schemas, enums and transition tables across web and API. | E41: Turborepo/Nx; two repos | F41: NFR-MNT-01, NFR-MNT-03 | G41: Proposed | H41: 2026-09-24
A42: D-20 | B42: Decision | C42: Deployment is Docker Compose now, then Vercel + Railway + Supabase on free tiers, with a verify-no-payment guardrail (ADR-0009). | D42: The primary run path (docker compose up) never depends on third parties, and the same images run in the cloud. | E42: Render-only; Vercel + Render + Neon | F42: NFR-POR-01, NFR-POR-04, DC-04, DR-11 | G42: Confirmed | H42: 2026-09-24 | I42: Chosen by product owner in architecture session
A43: D-21 | B43: Decision | C43: Tests use Vitest + Supertest against a real PostgreSQL test DB (ADR-0011). | D43: Locks and constraints can only be proven against the real engine. | E43: Jest; mocks/SQLite; Testcontainers | F43: DR-10, NFR-MNT-04 | G43: Proposed | H43: 2026-09-24
A44: D-22 | B44: Decision | C44: The frontend uses the Next.js App Router + TanStack Query (polling) + react-hook-form + Tailwind CSS (ADR-0012). | D44: Built-in loading/error states and polling; a small, maintainable UI stack. | E44: Vite + React Router; SWR; component libraries | F44: DC-01, FR-PAX-07, NFR-USA-01 | G44: Proposed | H44: 2026-09-24
A45: D-23 | B45: Decision | C45: Schema choices: pool_members link table, pools.capacity snapshot, driver_profiles table, zone code natural key, UUID ids, polymorphic append-only status_history (ERD §8). | D45: Row-local CHECK for capacity, re-matching history, driver-only ownership that is structural. | E45: ride_requests.pool_id; capacity via trigger; driver columns on users | F45: FR-POOL-02, FR-POOL-10, FR-HIST-02 | G45: Proposed | H45: 2026-09-24
A46: D-24 | B46: Decision | C46: Add an optional same-gender ride option, enforced as a pool-level restriction under the pool lock (BR-18). Fare rules unchanged. | D46: Improves rider comfort and safety with a minimal model change, reusing the existing lock and matching path. | E46: Driver-gender matching; mandatory gender; separate fare for restricted rides | F46: BR-18, FR-POOL-11, FR-POOL-12, FR-PAX-11 | G46: Confirmed | H46: 2026-09-24 | I46: Confirmed by product owner (same fare rules)
A47: P-01 | B47: PRD inconsistency | C47: The PRD mandates a master branch, but the repository was initialised with main. | D47: Create master and use it as the integration branch (DR-01). | F47: DR-01 | G47: Resolved | H47: 2026-09-23
A48: P-02 | B48: PRD inconsistency | C48: PRD §18 refers to "the concurrency problem in Section 14". It is actually in §12. | D48: Treated as §12. | F48: NFR-CON-01 | G48: Resolved | H48: 2026-09-23
A49: P-03 | B49: PRD inconsistency | C49: The PRD lifecycle mixes passenger-level and trip-level states. | D49: Split into two state machines (D-12). | F49: §5 | G49: Resolved | H49: 2026-09-23
A50: OI-01 | B50: Open issue | C50: Choose the backend framework, ORM, auth mechanism, test framework, styling and hosting, each justified per DC-07. | D50: Resolved 2026-09-24: D-14…D-22, ADR-0001…0012 | F50: DC-07, DR-07 | G50: Resolved | H50: 2026-09-24
A51: OI-02 | B51: Open issue | C51: Choose the concrete concurrency mechanism (pessimistic SELECT … FOR UPDATE versus a conditional update guarded by CHECK) and document it. | D51: Resolved 2026-09-24: row locks + CAS + constraints in layers (D-18, ADR-0006) | F51: NFR-CON-03 | G51: Resolved | H51: 2026-09-24
A52: OI-03 | B52: Open issue | C52: Decide whether the request-expiry sweeper runs as an in-process interval or lazily on read (NFR-REL-04 requires lazy correctness either way). | D52: Resolved 2026-09-24: expiry checked in accept CAS, plus 60 s in-process sweeper (D-18) | F52: NFR-REL-04 | G52: Resolved | H52: 2026-09-24

Sheet Implementation_Tasks
A1: Task ID | B1: Branch | C1: Description | D1: Req IDs | E1: Planned commit message | F1: Estimate (h) | G1: Status | H1: Actual commit(s) / PR | I1: Notes
A2: T-01 | B2: feature/srs-docs | C2: Write SRS (ISO/IEC/IEEE 29148) and traceability workbook | D2: DR-18 | E2: docs(srs): add software requirements specification and traceability workbook | F2: 6 | G2: In Review | I2: SRS v0.2 synced with ERD on 2026-09-24
A3: T-02 | B3: feature/architecture-docs | C3: Architecture diagram, ERD, tech-choice justifications (resolve OI-01..OI-03) | D3: DR-06, DR-07, DR-14, DC-01, DC-02, DC-03, DC-05, DC-07 | E3: docs(architecture): add system architecture diagram and ERD | F3: 5 | G3: In Review | H3: docs/ARCHITECTURE.md, docs/ERD.md, docs/adr/0001–0012 | I3: Drafted 2026-09-24; awaiting review
A4: T-03 | B4: feature/project-setup | C4: Scaffold web (Next.js) and api (Node.js, TypeScript) workspaces; lint, format, folder structure | D4: NFR-MNT-01, NFR-MNT-03, DC-01, DC-02 | E4: chore(repo): scaffold web and api workspaces | F4: 3 | G4: Done | H4: f221565 chore(repo), 9ddba2e docs(conventions) on feature/project-setup | I4: Also added docs/CODING_CONVENTIONS.md and config/rules.ts
A5: T-04 | B5: feature/project-setup | C5: API foundation: error handler & format, requestId, structured logging, security headers, CORS, schema validation | D5: NFR-REL-01, NFR-OBS-01, NFR-OBS-02, NFR-OBS-03, NFR-SEC-04, NFR-SEC-06, NFR-SEC-08, NFR-SEC-09 | E5: feat(api): add error handling, structured logging and request validation | F5: 4 | G5: Done | H5: 51da796 feat(api), 28caad4 refactor(api) on feature/project-setup | I5: Tests: apps/api/test/app.test.ts
A6: T-05 | B6: feature/project-setup | C6: Docker Compose (db, api, web), health checks, .env.example, /health endpoint | D6: NFR-POR-01, NFR-POR-02, NFR-REL-02, NFR-REL-03, NFR-SEC-05, DR-09, DC-03, DC-06 | E6: build(docker): add compose setup for api, web and postgres | F6: 4 | G6: Done | H6: 7d59b8d build(docker) on feature/project-setup | I6: Verified: 3 containers healthy, web page shows 'API ok', tests pass in container
A7: T-06 | B7: feature/db-schema | C7: Migrations for all entities with CHECK, unique/partial-unique constraints and indexes (SRS §7) | D7: NFR-CON-04, NFR-PERF-02, NFR-POR-03, FR-FARE-06, BR-14, FR-PAY-06, FR-HIST-02, FR-POOL-09, FR-POOL-10, BR-18 | E7: feat(db): add schema migrations with capacity and uniqueness constraints | F7: 6 | G7: Done | H7: e7db6c7 feat(db) schema, 77d5ab5 feat(db) integrity migration, 5c0b0e9 feat(db) helpers — feature/db-schema | I7: Prisma migrate diff shows no drift against the hand-written objects
A8: T-07 | B8: feature/db-schema | C8: Seed zones, distances, adjacency and reference personas (Nusrat, Rafiq, Shirin, Jashim/Bullet, Kamal/Toofan) with wallets | D8: BR-08, FR-AUTH-06, DR-15, NFR-POR-03 | E8: feat(seed): add Dhaka zones and reference persona seed data | F8: 3 | G8: Done | H8: b9272b5 feat(seed) — feature/db-schema | I8: Seed runs on container start; idempotent (TC-37)
A9: T-08 | B9: feature/passenger-auth | C9: Sign-up, sign-in, sign-out, /me with hashed passwords and secure session | D9: FR-AUTH-01, FR-AUTH-02, FR-AUTH-03, FR-AUTH-04, NFR-SEC-01, NFR-SEC-02, NFR-SEC-06 | E9: feat(auth): add passenger signup and login endpoints | F9: 5 | G9: Done | H9: 6ee7875 feat(shared), 0fccd56 feat(auth), 347e153 feat(auth) — feature/passenger-auth | I9: Sign-up, sign-in, sessions, sign-out, /me
A10: T-09 | B10: feature/passenger-auth | C10: Role guards, ownership checks, login rate limiting + authorization tests | D10: FR-AUTH-05, NFR-SEC-03, NFR-SEC-07 | E10: feat(auth): enforce role-based access and rate-limit login | F10: 3 | G10: Done | H10: 347e153 feat(auth) guards, cea26a4 feat(auth) rate limit, 07b28b6 test(auth) — feature/passenger-auth | I10: requireAuth/requireRole; 10 attempts/min per IP behind one trusted proxy hop
A11: T-10 | B11: feature/zones-fares | C11: Pure fare engine in paisa + unit tests for worked examples | D11: FR-FARE-01, BR-09, BR-10, BR-11, BR-12, BR-13, NFR-MNT-02 | E11: feat(fare): add paisa-based fare calculator with pool discount | F11: 3 | G11: Done | H11: b4e67b9 feat(fare), 1be55c0 test(fare), d9ff25f test(fare) — feature/zones-fares | I11: computeFare() and roundHalfUpDiv() on whole paisa; rates from CURRENT_FARE_RATES
A12: T-11 | B12: feature/zones-fares | C12: Zones and fare-estimate endpoints | D12: FR-PAX-01, FR-PAX-02, FR-FARE-02, FR-FARE-04 | E12: feat(fare): add zones and fare estimate endpoints | F12: 2 | G12: Done | H12: 2a5c39d feat(fare), 86a24c5 fix(api), 63be8bb test(fare) — feature/zones-fares | I12: GET /api/zones, POST /api/fares/estimate; zone reference data cached in memory
A13: T-12 | B13: feature/ride-request | C13: Ride & pool state machine module with transactional audit writer | D13: BR-06, FR-HIST-01, FR-HIST-02, FR-HIST-03, NFR-CON-02, NFR-MNT-02 | E13: feat(ride): add ride and pool state machines with audit trail | F13: 4 | G13: Done | H13: 97a8fb6 feat(ride) state machines, 97e9a70 feat(audit) — feature/ride-request | I13: Transition tables shared with the web app; audit writer inside the caller's transaction; WARN log for 409/422
A14: T-13 | B14: feature/ride-request | C14: Passenger ride endpoints: create, active/history, detail, cancel (with fee), expiry | D14: FR-PAX-03, FR-PAX-04, FR-PAX-05, FR-PAX-06, FR-PAX-08, FR-PAX-09, FR-PAX-10, BR-05, BR-07, FR-FARE-05, FR-HIST-04, NFR-REL-04, NFR-CON-06, FR-PAX-11 | E14: feat(ride): add passenger ride request lifecycle endpoints | F14: 6 | G14: In Progress | H14: 0896c40 feat(ride), e32e7bb fix(ride), dcc02ed feat(ride), 75785c0 test(ride) — feature/ride-request | I14: Create, list, detail, expiry and REQUESTED cancel done; cancelling MATCHED/DRIVER_ARRIVED (seat release, fee) comes with feature/tesla-pooling and feature/driver-flow
A15: T-14 | B15: feature/tesla-pooling | C15: Driver availability and relevant-request feed | D15: FR-DRV-01, FR-DRV-02, FR-DRV-03, FR-DRV-04 | E15: feat(driver): add online status and relevant request feed | F15: 4 | G15: Not Started | I15: Moved from feature/driver-flow: accept needs driver availability first (plan Phase 5)
A16: T-15 | B16: feature/tesla-pooling | C16: Accept into pool: matching rule, capacity lock, one active pool per driver | D16: FR-DRV-05, FR-POOL-01, FR-POOL-02, FR-POOL-03, FR-POOL-04, FR-POOL-05, FR-POOL-09, BR-01, BR-02, BR-03, BR-04, NFR-CON-01, NFR-CON-03, NFR-CON-04, FR-POOL-11, BR-18 | E16: feat(pool): enforce Bullet's seat capacity when accepting requests | F16: 6 | G16: Not Started
A17: T-16 | B17: feature/tesla-pooling | C17: Concurrency tests (last seat, double accept, cancel vs accept) and README concurrency notes | D17: NFR-CON-01, NFR-CON-02, DR-16 | E17: test(pool): add concurrent last-seat claim tests | F17: 3 | G17: Not Started
A18: T-17 | B18: feature/driver-flow | C18: Trip actions: arrive, start (fare lock), per-passenger drop-off, cancel pool, no-show, auto-complete/cancel | D18: FR-DRV-06, FR-DRV-07, FR-DRV-08, FR-DRV-09, FR-DRV-11, FR-DRV-12, FR-DRV-13, FR-FARE-03, FR-POOL-06, FR-POOL-07, FR-POOL-08, FR-POOL-12 | E18: feat(driver): add arrive, start and drop-off trip actions | F18: 6 | G18: Not Started
A19: T-18 | B19: feature/teslapay-wallet | C19: Wallet, top-up, ledger, ride settlement, cash collection, cancellation-fee debit | D19: FR-PAY-01, FR-PAY-02, FR-PAY-03, FR-PAY-04, FR-PAY-05, FR-PAY-06, FR-DRV-10, BR-15, BR-16, BR-17, NFR-CON-05 | E19: feat(wallet): add simulated TeslaPay wallet and ride settlement | F19: 5 | G19: Not Started
A20: T-19 | B20: feature/passenger-ui | C20: Web: sign-in/sign-up pages, layout, role routing, API client, shared loading/empty/error components | D20: FR-AUTH-05, NFR-USA-01, NFR-USA-05 | E20: feat(web): add sign-in, sign-up and role-based routing | F20: 4 | G20: Not Started
A21: T-20 | B21: feature/passenger-ui | C21: Web: request ride with live estimate; current-ride tracker with polling; cancel dialog | D21: FR-PAX-02, FR-PAX-06, FR-PAX-07, FR-PAX-08, NFR-USA-02, NFR-USA-03, NFR-USA-04, NFR-USA-06, NFR-PERF-03, FR-PAX-11 | E21: feat(web): add ride request form and live status tracker | F21: 6 | G21: Not Started
A22: T-21 | B22: feature/passenger-ui | C22: Web: ride history, ride detail timeline, TeslaPay wallet pages | D22: FR-PAX-09, FR-PAX-10, FR-PAY-01, FR-PAY-02 | E22: feat(web): add ride history and TeslaPay wallet pages | F22: 4 | G22: Not Started
A23: T-22 | B23: feature/driver-ui | C23: Web: driver dashboard, request feed, active pool management, history | D23: FR-DRV-01, FR-DRV-02, FR-DRV-04, FR-DRV-06, FR-DRV-07, FR-DRV-08, FR-DRV-09, FR-DRV-10, FR-DRV-11, FR-DRV-13, NFR-USA-03, NFR-USA-06 | E23: feat(web): add driver dashboard and pool management screens | F23: 6 | G23: Not Started
A24: T-23 | B24: pre-release | C24: Integration fixes, end-to-end walkthrough, performance smoke test, single test command | D24: NFR-PERF-01, NFR-MNT-04, DR-10 | E24: fix(<scope>): <integration issue> (one commit per fix) | F24: 4 | G24: Not Started
A25: T-24 | B25: pre-release | C25: README: setup, API overview, decisions/trade-offs, limitations, AI usage, screenshots | D25: DR-05, DR-07, DR-08, DR-16 | E25: docs(readme): document setup, decisions and AI usage | F25: 4 | G25: Not Started
A26: T-25 | B26: pre-release | C26: Free-tier public deployment (or documented reproducible Docker fallback) | D26: NFR-POR-04, DR-11, DC-04, DR-13 | E26: build(deploy): add free-tier deployment configuration | F26: 4 | G26: Not Started
A27: T-26 | B27: pre-release | C27: Viral-scale bonus section with diagram (1M passengers / 100k drivers) | D27: DR-17 | E27: docs(scaling): add viral-scale design notes | F27: 3 | G27: Not Started
A28: T-27 | B28: release/v1.0.0 | C28: Cut release/v1.0.0 from pre-release, record ≤6-min video, link in README; verify branch/commit history | D28: DR-01, DR-02, DR-03, DR-04, DR-12 | E28: chore(release): prepare v1.0.0 | F28: 3 | G28: Not Started
E29: Total estimate (h) | F29: =SUM(F2:F28)
E30: Remaining (h, not Done) | F30: =SUMIFS(F2:F28,G2:G28,"<>Done")
A31: Branch flow (PRD §10): feature/* → master (when working) → pre-release (integration, docs, deploy) → release/v1.0.0. Estimates are the author's planning guesses.

Sheet State_Transitions
A1: Transition | B1: Machine | C1: From | D1: To | E1: Actor | F1: Guard(s) | G1: Side effects
A2: RT-01 | B2: Ride request | C2: — | D2: REQUESTED | E2: Passenger (owner) | F2: FR-PAX-03 validation; no active request (BR-05) | G2: Estimate stored; audit
A3: RT-02 | B3: Ride request | C3: REQUESTED | D3: MATCHED | E3: Driver | F3: Driver ONLINE; request not expired; BR-01…BR-04 | G3: Pool created or joined; seats claimed; audit
A4: RT-03 | B4: Ride request | C4: REQUESTED | D4: CANCELLED | E4: Passenger (owner) | F4: — | G4: Audit (free)
A5: RT-04 | B5: Ride request | C5: REQUESTED | D5: EXPIRED | E5: System | F5: 15 min in REQUESTED (A-13) | G5: Audit
A6: RT-05 | B6: Ride request | C6: MATCHED | D6: DRIVER_ARRIVED | E6: Driver (pool owner) | F6: Cascade of PT-02 | G6: Audit
A7: RT-06 | B7: Ride request | C7: MATCHED | D7: CANCELLED | E7: Passenger (owner) | F7: — | G7: Seats freed; maybe auto-cancel pool (FR-POOL-07); audit (free)
A8: RT-07 | B8: Ride request | C8: MATCHED | D8: REQUESTED | E8: Driver (pool owner) | F8: Cascade of PT-04 | G8: Membership ended; seats freed; expiry timer restarts; audit
A9: RT-08 | B9: Ride request | C9: DRIVER_ARRIVED | D9: STARTED | E9: Driver (pool owner) | F9: Cascade of PT-03 | G9: Fare locked (BR-12); audit
A10: RT-09 | B10: Ride request | C10: DRIVER_ARRIVED | D10: CANCELLED | E10: Passenger (owner) or Driver (no-show, ≥5 min, C) | F10: — | G10: ৳20 fee (BR-07); seats freed; audit
A11: RT-10 | B11: Ride request | C11: DRIVER_ARRIVED | D11: REQUESTED | E11: Driver (pool owner) | F11: Cascade of PT-04 | G11: As RT-07, no fee
A12: RT-11 | B12: Ride request | C12: STARTED | D12: COMPLETED | E12: Driver (pool owner) | F12: Member belongs to driver's STARTED pool | G12: Payment settlement (BR-15/16); maybe auto-complete pool; audit
... A18: PT-06 | B18: Pool | C18: STARTED | D18: COMPLETED | E18: System | F18: Every on-board member COMPLETED | G18: Driver's zone := last drop-off zone
A20: Ride request — allowed transitions matrix (P = passenger, D = driver, S = system; blank = rejected with 409)
A21: From \ To | B21: REQUESTED | C21: MATCHED | D21: DRIVER_ARRIVED | E21: STARTED | F21: COMPLETED | G21: CANCELLED | H21: EXPIRED
A22: REQUESTED | C22: D | G22: P | H22: S
A23: MATCHED | B23: D | D23: D | G23: P
A24: DRIVER_ARRIVED | B24: D | E24: D | G24: P, D (no-show)
A25: STARTED | F25: D
A26: COMPLETED
A27: CANCELLED
A28: EXPIRED
A30: Pool — allowed transitions matrix
A31: From \ To | B31: OPEN | C31: DRIVER_ARRIVED | D31: STARTED | E31: COMPLETED | F31: CANCELLED
A32: OPEN | B32: D (add member) | C32: D | F32: D, S
A33: DRIVER_ARRIVED | D33: D | F33: D, S
A34: STARTED | E34: S
A35: COMPLETED
A36: CANCELLED

Sheet Zones_Distances
A1: Zones (SRS §13.3)
A2: Code | B2: Zone | C2: Lat | D2: Lng | E2: Adjacent to
A3: BAN | B3: Banani | C3: 23.7937 | D3: 90.4066 | E3: GL1, GL2, MHK
A4: GL1 | B4: Gulshan 1 | C4: 23.7808 | D4: 90.4169 | E4: BAN, GL2, MHK, TEJ
A5: GL2 | B5: Gulshan 2 | C5: 23.7925 | D5: 90.4155 | E5: BAN, GL1, BSH
A6: MHK | B6: Mohakhali | C6: 23.778 | D6: 90.405 | E6: BAN, GL1, TEJ
A7: TEJ | B7: Tejgaon | C7: 23.764 | D7: 90.393 | E7: GL1, MHK, FRM
A8: FRM | B8: Farmgate | C8: 23.7561 | D8: 90.3872 | E8: TEJ, DHN, MIR
A9: DHN | B9: Dhanmondi | C9: 23.7461 | D9: 90.3742 | E9: FRM
A10: MIR | B10: Mirpur | C10: 23.8069 | D10: 90.3687 | E10: FRM
A11: UTR | B11: Uttara | C11: 23.8759 | D11: 90.3795 | E11: BSH
A12: BSH | B12: Bashundhara | C12: 23.8193 | D12: 90.4526 | E12: GL2, UTR
A14: Road-approximation distance (km, symmetric). Blue = reference input; edit only with an SRS change.
A15: From \ To | B15: BAN | C15: GL1 | D15: GL2 | E15: MHK | F15: TEJ | G15: FRM | H15: DHN | I15: MIR | J15: UTR | K15: BSH
A16: BAN | B16: 0 | C16: 2.5 | D16: 2 | E16: 3 | F16: 5 | G16: 7 | H16: 10 | I16: 8.5 | J16: 11 | K16: 5.5
A17: GL1 | B17: 2.5 | C17: 0 | D17: 2 | E17: 2.5 | F17: 4 | G17: 6.5 | H17: 9.5 | I17: 10 | J17: 13 | K17: 6
A18: GL2 | B18: 2 | C18: 2 | D18: 0 | E18: 4 | F18: 5.5 | G18: 8 | H18: 11 | I18: 10 | J18: 12 | K18: 4.5
A19: MHK | B19: 3 | C19: 2.5 | D19: 4 | E19: 0 | F19: 2.5 | G19: 4.5 | H19: 7.5 | I19: 8 | J19: 13.5 | K19: 7.5
A20: TEJ | B20: 5 | C20: 4 | D20: 5.5 | E20: 2.5 | F20: 0 | G20: 2.5 | H20: 5.5 | I20: 8.5 | J20: 15 | K20: 8.5
A21: FRM | B21: 7 | C21: 6.5 | D21: 8 | E21: 4.5 | F21: 2.5 | G21: 0 | H21: 3.5 | I21: 7 | J21: 17 | K21: 10.5
A22: DHN | B22: 10 | C22: 9.5 | D22: 11 | E22: 7.5 | F22: 5.5 | G22: 3.5 | H22: 0 | I22: 8 | J22: 20 | K22: 13.5
A23: MIR | B23: 8.5 | C23: 10 | D23: 10 | E23: 8 | F23: 8.5 | G23: 7 | H23: 8 | I23: 0 | J23: 12 | K23: 11.5
A24: UTR | B24: 11 | C24: 13 | D24: 12 | E24: 13.5 | F24: 15 | G24: 17 | H24: 20 | I24: 12 | J24: 0 | K24: 9
A25: BSH | B25: 5.5 | C25: 6 | D25: 4.5 | E25: 7.5 | F25: 8.5 | G25: 10.5 | H25: 13.5 | I25: 11.5 | J25: 9 | K25: 0
A27: Symmetry check (asymmetric cells): | D27: =SUMPRODUCT(--(B16:K25<>TRANSPOSE(B16:K25))) | E27: must be 0

Sheet Fare_Calculator
A1: Fare calculator — BR-10 (hand-verifiable, all amounts in paisa)
A2: Blue cells are inputs. Yellow row is a free-play row. Formula: distanceCharge = ROUND(distance_m × perKm / 1000); discount = pooled ? ROUND(distanceCharge × bps / 10000) : 0; perSeat = base + distanceCharge − discount; total = perSeat × seats.
A4: Rates (BR-11)
A5: Base fare (paisa) | C5: 3000 | D5: Source: SRS BR-11 (user-confirmed fare model D-06)
A6: Per km (paisa) | C6: 1500
A7: Pool discount (bps of distance charge) | C7: 2000
A8: Cancellation fee (paisa) | C8: 2000
A11: Scenario | B11: Passenger | C11: Pickup | D11: Destination | E11: Seats | F11: Pooled (Y/N) | G11: Distance (m) | H11: Distance charge | I11: Pool discount | J11: Fare per seat | K11: Total (paisa) | L11: Total (৳) | M11: Expected (SRS §6.4) | N11: Check
A12: E1 pooled | B12: Nusrat | C12: BAN | D12: MHK | E12: 1 | F12: Y | G12: =INDEX(Zones_Distances!$B$16:$K$25,MATCH(C12,Zones_Distances!$A$16:$A$25,0),MATCH(D12,Zones_Distances!$B$15:$K$15,0))*1000 | H12: =ROUND(G12*$C$6/1000,0) | I12: =IF(F12="Y",ROUND(H12*$C$7/10000,0),0) | J12: =$C$5+H12-I12 | K12: =J12*E12 | L12: =K12/100 | M12: 6600 | N12: =IF(M12="","—",IF(K12=M12,"OK","MISMATCH"))
A13: E1 pooled | B13: Rafiq | C13: BAN | D13: GL1 | E13: 1 | F13: Y | G13: =INDEX(Zones_Distances!$B$16:$K$25,MATCH(C13,Zones_Distances!$A$16:$A$25,0),MATCH(D13,Zones_Distances!$B$15:$K$15,0))*1000 | H13: =ROUND(G13*$C$6/1000,0) | I13: =IF(F13="Y",ROUND(H13*$C$7/10000,0),0) | J13: =$C$5+H13-I13 | K13: =J13*E13 | L13: =K13/100 | M13: 6000 | N13: =IF(M13="","—",IF(K13=M13,"OK","MISMATCH"))
A14: Solo | B14: Nusrat | C14: BAN | D14: MHK | E14: 1 | F14: N | G14: =INDEX(Zones_Distances!$B$16:$K$25,MATCH(C14,Zones_Distances!$A$16:$A$25,0),MATCH(D14,Zones_Distances!$B$15:$K$15,0))*1000 | H14: =ROUND(G14*$C$6/1000,0) | I14: =IF(F14="Y",ROUND(H14*$C$7/10000,0),0) | J14: =$C$5+H14-I14 | K14: =J14*E14 | L14: =K14/100 | M14: 7500 | N14: =IF(M14="","—",IF(K14=M14,"OK","MISMATCH"))
A15: Solo | B15: Rafiq | C15: BAN | D15: GL1 | E15: 1 | F15: N | G15: =INDEX(Zones_Distances!$B$16:$K$25,MATCH(C15,Zones_Distances!$A$16:$A$25,0),MATCH(D15,Zones_Distances!$B$15:$K$15,0))*1000 | H15: =ROUND(G15*$C$6/1000,0) | I15: =IF(F15="Y",ROUND(H15*$C$7/10000,0),0) | J15: =$C$5+H15-I15 | K15: =J15*E15 | L15: =K15/100 | M15: 6750 | N15: =IF(M15="","—",IF(K15=M15,"OK","MISMATCH"))
A16: Pooled (3rd seat) | B16: Shirin | C16: BAN | D16: TEJ | E16: 1 | F16: Y | G16: =INDEX(Zones_Distances!$B$16:$K$25,MATCH(C16,Zones_Distances!$A$16:$A$25,0),MATCH(D16,Zones_Distances!$B$15:$K$15,0))*1000 | H16: =ROUND(G16*$C$6/1000,0) | I16: =IF(F16="Y",ROUND(H16*$C$7/10000,0),0) | J16: =$C$5+H16-I16 | K16: =J16*E16 | L16: =K16/100 | M16: 9000 | N16: =IF(M16="","—",IF(K16=M16,"OK","MISMATCH"))
A17: Solo | B17: Shirin | C17: BAN | D17: TEJ | E17: 1 | F17: N | G17: =INDEX(Zones_Distances!$B$16:$K$25,MATCH(C17,Zones_Distances!$A$16:$A$25,0),MATCH(D17,Zones_Distances!$B$15:$K$15,0))*1000 | H17: =ROUND(G17*$C$6/1000,0) | I17: =IF(F17="Y",ROUND(H17*$C$7/10000,0),0) | J17: =$C$5+H17-I17 | K17: =J17*E17 | L17: =K17/100 | M17: 10500 | N17: =IF(M17="","—",IF(K17=M17,"OK","MISMATCH"))
A18: E4 two seats solo | B18: Nusrat | C18: BAN | D18: MHK | E18: 2 | F18: N | G18: =INDEX(Zones_Distances!$B$16:$K$25,MATCH(C18,Zones_Distances!$A$16:$A$25,0),MATCH(D18,Zones_Distances!$B$15:$K$15,0))*1000 | H18: =ROUND(G18*$C$6/1000,0) | I18: =IF(F18="Y",ROUND(H18*$C$7/10000,0),0) | J18: =$C$5+H18-I18 | K18: =J18*E18 | L18: =K18/100 | M18: 15000 | N18: =IF(M18="","—",IF(K18=M18,"OK","MISMATCH"))
A19: Try your own | B19: (any) | C19: GL2 | D19: BSH | E19: 1 | F19: Y | G19: =INDEX(Zones_Distances!$B$16:$K$25,MATCH(C19,Zones_Distances!$A$16:$A$25,0),MATCH(D19,Zones_Distances!$B$15:$K$15,0))*1000 | H19: =ROUND(G19*$C$6/1000,0) | I19: =IF(F19="Y",ROUND(H19*$C$7/10000,0),0) | J19: =$C$5+H19-I19 | K19: =J19*E19 | L19: =K19/100 | N19: =IF(M19="","—",IF(K19=M19,"OK","MISMATCH"))
A21: E1 saving for the two riders together (৳) | L21: =(K14+K15-K12-K13)/100 | M21: 16.5 | N21: =IF(ABS(L21-M21)<0.001,"OK","MISMATCH")

Sheet Glossary
A1: Term | B1: Definition
A2: Tesla | B2: Fictional name for a three-wheeled battery rickshaw. In the system it is a vehicle with a fixed seat capacity.
A3: Zone | B3: One of a predefined list of Dhaka areas (e.g. Banani, Mohakhali), with a code, a name and a representative lat/long.
A4: Ride request | B4: One passenger's request for a trip: pickup zone, destination zone, seats, pool opt-in and payment method. It has its own lifecycle (§5.1).
A5: Pool | B5: One trip of one Tesla, carrying one or more ride requests from the same pickup zone. It has its own lifecycle (§5.2). "Ride" and "pool" are used interchangeably from the driver's side.
A6: Pool member | B6: A ride request assigned to a pool.
A7: Occupied seats | B7: Sum of seats over a pool's members that are in an active status (MATCHED, DRIVER_ARRIVED, STARTED).
A8: Pooled | B8: A pool is pooled when two or more distinct ride requests (from different passengers) are on board at trip start.
A9: Paisa (poysha) | B9: 1/100 of a Bangladeshi Taka (৳). All money is stored as an integer number of paisa.
A10: TeslaPay | B10: Simulated in-app wallet. There is no real money and no real gateway.
A11: Active request | B11: A ride request in REQUESTED, MATCHED, DRIVER_ARRIVED or STARTED status.
A12: Active pool | B12: A pool in OPEN, DRIVER_ARRIVED or STARTED status.
... A16: MoSCoW | B16: Must / Should / Could / Won't prioritisation

Sheet PRD_Coverage
A1: PRD § | B1: Section title | C1: # requirements tracing here | D1: Covered by (non-requirement) | E1: Coverage
A2: 1 | B2: The Banani Rush-Hour Story | C2: =COUNTIF(Requirements_RTM!$P$2:$P$142,"*,"&A2&",*") | E2: =IF(C2>0,"Covered",IF(D2<>"","Covered (see note)","GAP"))
A3: 2 | B3: The Product Problem | C3: =COUNTIF(Requirements_RTM!$P$2:$P$142,"*,"&A3&",*") | E3: =IF(C3>0,"Covered",IF(D3<>"","Covered (see note)","GAP"))
A4: 3 | B4: Your Mission: Build the MVP | C4: =COUNTIF(Requirements_RTM!$P$2:$P$142,"*,"&A4&",*") | E4: =IF(C4>0,"Covered",IF(D4<>"","Covered (see note)","GAP"))
A5: 4 | B5: Keeping Geography Simple | C5: =COUNTIF(Requirements_RTM!$P$2:$P$142,"*,"&A5&",*") | E5: =IF(C5>0,"Covered",IF(D5<>"","Covered (see note)","GAP"))
A6: 5 | B6: Fare Model | C6: =COUNTIF(Requirements_RTM!$P$2:$P$142,"*,"&A6&",*") | E6: =IF(C6>0,"Covered",IF(D6<>"","Covered (see note)","GAP"))
A7: 6 | B7: Technical Scope & Mandated Stack | C7: =COUNTIF(Requirements_RTM!$P$2:$P$142,"*,"&A7&",*") | E7: =IF(C7>0,"Covered",IF(D7<>"","Covered (see note)","GAP"))
A8: 7 | B8: Technology Choice & Justification | C8: =COUNTIF(Requirements_RTM!$P$2:$P$142,"*,"&A8&",*") | E8: =IF(C8>0,"Covered",IF(D8<>"","Covered (see note)","GAP"))
A9: 8 | B9: AI Usage Policy | C9: =COUNTIF(Requirements_RTM!$P$2:$P$142,"*,"&A9&",*") | E9: =IF(C9>0,"Covered",IF(D9<>"","Covered (see note)","GAP"))
A10: 9 | B10: Architecture First | C10: =COUNTIF(Requirements_RTM!$P$2:$P$142,"*,"&A10&",*") | E10: =IF(C10>0,"Covered",IF(D10<>"","Covered (see note)","GAP"))
A11: 10 | B11: Git Workflow | C11: =COUNTIF(Requirements_RTM!$P$2:$P$142,"*,"&A11&",*") | E11: =IF(C11>0,"Covered",IF(D11<>"","Covered (see note)","GAP"))
A12: 11 | B12: Commit Message Rules | C12: =COUNTIF(Requirements_RTM!$P$2:$P$142,"*,"&A12&",*") | E12: =IF(C12>0,"Covered",IF(D12<>"","Covered (see note)","GAP"))
A13: 12 | B13: README, Testing, Concurrency & Bonus | C13: =COUNTIF(Requirements_RTM!$P$2:$P$142,"*,"&A13&",*") | E13: =IF(C13>0,"Covered",IF(D13<>"","Covered (see note)","GAP"))
... A15: 14 | B15: Submission Checklist | C15: =COUNTIF(Requirements_RTM!$P$2:$P$142,"*,"&A15&",*") | E15: =IF(C15>0,"Covered",IF(D15<>"","Covered (see note)","GAP"))
A16: 15 | B16: What We Will Evaluate | C16: =COUNTIF(Requirements_RTM!$P$2:$P$142,"*,"&A16&",*") | D16: Evaluation criteria; addressed by the SRS as a whole and Verification (§12) | E16: =IF(C16>0,"Covered",IF(D16<>"","Covered (see note)","GAP"))
A17: 16 | B17: What NOT to Do | C17: =COUNTIF(Requirements_RTM!$P$2:$P$142,"*,"&A17&",*") | E17: =IF(C17>0,"Covered",IF(D17<>"","Covered (see note)","GAP"))
A18: 17 | B18: Assumptions Are Allowed | C18: =COUNTIF(Requirements_RTM!$P$2:$P$142,"*,"&A18&",*") | D18: Assumptions register A-01…A-18 (Assumptions_Decisions) | E18: =IF(C18>0,"Covered",IF(D18<>"","Covered (see note)","GAP"))
A19: 18 | B19: Why the Details Matter | C19: =COUNTIF(Requirements_RTM!$P$2:$P$142,"*,"&A19&",*") | E19: =IF(C19>0,"Covered",IF(D19<>"","Covered (see note)","GAP"))
A20: 19 | B20: Final Note From RoBenDevs | C20: =COUNTIF(Requirements_RTM!$P$2:$P$142,"*,"&A20&",*") | D20: Informational only — no requirement | E20: =IF(C20>0,"Covered",IF(D20<>"","Covered (see note)","GAP"))
